rtl/riscv/riscv.sv
`default_nettype none

/* verilator lint_off DECLFILENAME */
/* verilator lint_off UNUSED */

// Instruction Fetch Unit
module riscv_ifu
(
  input wire logic clk_i,
  input wire logic reset_ni,

  // New PC (for jumps and branches)
  // This will invalidate any currently processing instructions
  input wire logic pc_valid_i,
  input wire logic [29:0] pc_i,

  // Interface to IDU
  input wire logic instr_ready_i,
  output logic instr_valid_o,
  output logic [31:0] instr_o,

  // Master port
  input wire logic wb_ack_i,
  input wire logic wb_stall_i,
  input wire logic wb_err_i,
  input wire logic [31:0] wb_data_i,
  output logic [31:0] wb_data_o,
  output logic [29:0] wb_addr_o,
  output logic [3:0] wb_sel_o,
  output logic wb_cyc_o,
  output logic wb_stb_o,
  output logic wb_we_o
);

logic [29:0] pc_q;
logic [31:0] instr_q;
logic instr_valid_q;
logic cyc_q;
logic stb_q;
logic invalid_q; // Skip next ack

assign wb_sel_o = '0;
assign wb_data_o = '0;
assign wb_we_o = '0;

assign instr_o = instr_q;
assign instr_valid_o = instr_valid_q;
assign wb_cyc_o = cyc_q;
assign wb_stb_o = stb_q;
assign wb_addr_o = pc_q;

initial pc_q = '0;
initial instr_valid_q = '0;
initial cyc_q = '0;
initial stb_q = '0;
initial invalid_q = '0;

always_ff @(posedge clk_i) begin
  if((!reset_ni) || (!cyc_q) ) begin
    invalid_q <= '0;
  end else if(pc_valid_i) begin
    invalid_q <= '1;
  end
end

always_ff @(posedge clk_i) begin
  if((!reset_ni) || (cyc_q && wb_ack_i)) begin
    cyc_q <= '0;
    stb_q <= '0;
  end else if(!cyc_q && (!instr_valid_o)) begin
    cyc_q <= '1;
    stb_q <= '1;
  end else if(cyc_q) begin
    cyc_q <= '1;
    if(!wb_stall_i) begin
      stb_q <= '0;
    end
  end
end

always_ff @(posedge clk_i) begin
  if(wb_cyc_o && wb_ack_i) begin
    instr_q <= wb_data_i;
  end
end

always_ff @(posedge clk_i) begin
  if(pc_valid_i) begin
    pc_q <= pc_i;
  end else if(instr_valid_q && instr_ready_i) begin
    pc_q <= pc_q + 1'b1;
  end
end

always_ff @(posedge clk_i) begin
  if((!reset_ni) || pc_valid_i) begin
    instr_valid_q <= '0;
  end else if(wb_cyc_o && wb_ack_i && !invalid_q) begin
    instr_valid_q <= '1;
  end else if(instr_ready_i) begin
    instr_valid_q <= '0;
  end
end

endmodule



module riscv_dummy
(
  input wire logic clk_i,
  input wire logic reset_ni,

  input wire logic clear_i,

  input wire logic [31:0] instr_i,
  input wire logic instr_valid_i,
  output logic instr_ready_o,

  output logic [31:0] instr_o,
  output logic instr_valid_o,
  input wire logic instr_ready_i
);

logic [31:0] instr_q;
logic instr_valid_q;
logic instr_ready_q;

initial instr_valid_q = '0;
initial instr_ready_q = '1;

assign instr_o = instr_q;
assign instr_valid_o = instr_valid_q;
assign instr_ready_o = instr_ready_q;

always_ff @(posedge clk_i) begin
  if((!reset_ni) || clear_i) begin
    instr_valid_q <= '0;
    instr_ready_q <= '1;
  end else if(instr_valid_i && !instr_valid_o) begin
    instr_q <= instr_i;
    instr_valid_q <= '1;
    instr_ready_q <= '0;
  end else if(instr_valid_q && instr_ready_i) begin
    instr_valid_q <= '0;
    instr_ready_q <= '1;
  end

  //instr_ready_q <= instr_ready_i;
end

endmodule

module riscv_dummy_branch
(
  input wire logic clk_i,
  input wire logic reset_ni,

  input wire logic [31:0] instr_i,
  input wire logic instr_valid_i,
  output logic instr_ready_o,

  output logic pc_valid_o
);

logic [31:0] timer;
initial timer = '0;
always_ff @(posedge clk_i) begin
  timer <= timer + 1;
end

initial pc_valid_o = '0;

assign instr_ready_o = timer >= 8 ? '1 : '0;

always_ff @(posedge clk_i) begin
  if(!reset_ni) begin
    pc_valid_o <= '0;
  end else begin
    if(instr_valid_i && instr_i == 32'hDEADBEEF) begin
      pc_valid_o <= '1;
    end else begin
      pc_valid_o <= '0;
    end
  end
end

endmodule

module riscv
(
  input wire logic clk_i,
  input wire logic reset_ni,

  // Instruction Port
  input wire logic wb_i_ack_i,
  input wire logic wb_i_stall_i,
  input wire logic wb_i_err_i,
  input wire logic [31:0] wb_i_data_i,
  output logic [31:0] wb_i_data_o,
  output logic [29:0] wb_i_addr_o,
  output logic [3:0] wb_i_sel_o,
  output logic wb_i_cyc_o,
  output logic wb_i_stb_o,
  output logic wb_i_we_o
);

logic [31:0] ifu_instr;
logic ifu_valid;
logic ifu_ready;

logic ifu_pc_valid;

logic [31:0] dummy_instr;
logic dummy_valid;
logic dummy_ready;

riscv_dummy dummy0
(
  .clk_i,
  .reset_ni,

  .clear_i(ifu_pc_valid),

  .instr_i(ifu_instr),
  .instr_valid_i(ifu_valid),
  .instr_ready_o(ifu_ready),

  .instr_valid_o(dummy_valid),
  .instr_o(dummy_instr),
  .instr_ready_i(dummy_ready)
);

riscv_dummy_branch branch0
(
  .clk_i,
  .reset_ni,

  .instr_i(dummy_instr),
  .instr_valid_i(dummy_valid),
  .instr_ready_o(dummy_ready),

  .pc_valid_o(ifu_pc_valid)
);

riscv_ifu ifu0
(
  .clk_i,
  .reset_ni,

  // Tie ready to high
  .instr_ready_i(ifu_ready),
  .instr_valid_o(ifu_valid),
  .instr_o(ifu_instr),

  .pc_i(1),
  .pc_valid_i(ifu_pc_valid),

  .wb_ack_i(wb_i_ack_i),
  .wb_stall_i(wb_i_stall_i),
  .wb_err_i(wb_i_err_i),
  .wb_data_i(wb_i_data_i),
  .wb_data_o(wb_i_data_o),
  .wb_addr_o(wb_i_addr_o),
  .wb_sel_o(wb_i_sel_o),
  .wb_cyc_o(wb_i_cyc_o),
  .wb_stb_o(wb_i_stb_o),
  .wb_we_o(wb_i_we_o)
);

endmodule

rtl/rom.sv
`default_nettype none

/* verilator lint_off UNUSED */

module rom
#(
  parameter Contents = "",
  parameter Depth = 0,

  localparam DataWidth = 32,
  localparam AddrWidth = $clog2(Depth),
  localparam SelWidth = DataWidth / 8
)
(
  input wire logic clk,

  output logic [DataWidth-1:0] bus_data_s,
  output logic bus_ack,
  output logic bus_stall,
  output logic bus_err,

  input wire logic [DataWidth-1:0] bus_data_m,
  input wire logic [AddrWidth-1:0] bus_addr,
  input wire logic [SelWidth-1:0] bus_sel,
  input wire logic bus_cyc,
  input wire logic bus_stb,
  input wire logic bus_we
);

logic [DataWidth-1:0] mem [0:Depth-1];

initial begin
  bus_ack = '0;

  $readmemh(Contents, mem);
end

assign bus_err = '0;
assign bus_stall = '0;

always_ff @(posedge clk) begin
  bus_data_s <= mem[bus_addr];
  bus_ack <= bus_stb;
end

endmodule

rtl/sim/riscv_top.sv
`default_nettype none

/* verilator lint_off UNUSED */

module riscv_top
(
  input wire logic clk_i,
  input wire logic reset_ni,
  output logic [3:0] leds_o
);

// Rom
logic [31:0] rom_data_s;
logic rom_ack;
logic rom_stall;
logic rom_err;
logic [31:0] rom_data_m;
logic [29:0] rom_addr;
logic [3:0] rom_sel;
logic rom_cyc;
logic rom_stb;
logic rom_we;

assign leds_o = '0;

rom
#(
  .Contents("test.mem"),
  .Depth(4096) //16 Kilobytes
) rom0
(
  .clk(clk_i),

  .bus_data_s(rom_data_s),
  .bus_ack(rom_ack),
  .bus_stall(rom_stall),
  .bus_err(rom_err),
  .bus_data_m(rom_data_m),
  .bus_addr(rom_addr[11:0]),
  .bus_sel(rom_sel),
  .bus_cyc(rom_cyc),
  .bus_stb(rom_stb),
  .bus_we(rom_we)
);

riscv cpu0
(
  .clk_i,
  .reset_ni,

  .wb_i_data_i(rom_data_s),
  .wb_i_ack_i(rom_ack),
  .wb_i_stall_i(rom_stall),
  .wb_i_err_i(rom_err),
  .wb_i_data_o(rom_data_m),
  .wb_i_addr_o(rom_addr),
  .wb_i_sel_o(rom_sel),
  .wb_i_cyc_o(rom_cyc),
  .wb_i_stb_o(rom_stb),
  .wb_i_we_o(rom_we)
);

endmodule

sim/riscv/trace.vcd
$version Generated by VerilatedVcd $end
$date Wed Nov  9 22:39:58 2022 $end
$timescale 1ps $end

 $scope module TOP $end
  $var wire  1 2 clk_i $end
  $var wire  4 4 leds_o [3:0] $end
  $var wire  1 3 reset_ni $end
  $scope module riscv_top $end
   $var wire  1 2 clk_i $end
   $var wire  4 4 leds_o [3:0] $end
   $var wire  1 3 reset_ni $end
   $var wire  1 $ rom_ack $end
   $var wire 30 % rom_addr [29:0] $end
   $var wire  1 & rom_cyc $end
   $var wire 32 6 rom_data_m [31:0] $end
   $var wire 32 # rom_data_s [31:0] $end
   $var wire  1 5 rom_err $end
   $var wire  4 7 rom_sel [3:0] $end
   $var wire  1 5 rom_stall $end
   $var wire  1 ' rom_stb $end
   $var wire  1 5 rom_we $end
   $scope module cpu0 $end
    $var wire  1 2 clk_i $end
    $var wire 32 , dummy_instr [31:0] $end
    $var wire  1 . dummy_ready $end
    $var wire  1 - dummy_valid $end
    $var wire 32 ( ifu_instr [31:0] $end
    $var wire  1 + ifu_pc_valid $end
    $var wire  1 * ifu_ready $end
    $var wire  1 ) ifu_valid $end
    $var wire  1 3 reset_ni $end
    $var wire  1 $ wb_i_ack_i $end
    $var wire 30 % wb_i_addr_o [29:0] $end
    $var wire  1 & wb_i_cyc_o $end
    $var wire 32 # wb_i_data_i [31:0] $end
    $var wire 32 6 wb_i_data_o [31:0] $end
    $var wire  1 5 wb_i_err_i $end
    $var wire  4 7 wb_i_sel_o [3:0] $end
    $var wire  1 5 wb_i_stall_i $end
    $var wire  1 ' wb_i_stb_o $end
    $var wire  1 5 wb_i_we_o $end
    $scope module branch0 $end
     $var wire  1 2 clk_i $end
     $var wire 32 , instr_i [31:0] $end
     $var wire  1 . instr_ready_o $end
     $var wire  1 - instr_valid_i $end
     $var wire  1 + pc_valid_o $end
     $var wire  1 3 reset_ni $end
     $var wire 32 / timer [31:0] $end
    $upscope $end
    $scope module dummy0 $end
     $var wire  1 + clear_i $end
     $var wire  1 2 clk_i $end
     $var wire 32 ( instr_i [31:0] $end
     $var wire 32 , instr_o [31:0] $end
     $var wire 32 , instr_q [31:0] $end
     $var wire  1 . instr_ready_i $end
     $var wire  1 * instr_ready_o $end
     $var wire  1 * instr_ready_q $end
     $var wire  1 ) instr_valid_i $end
     $var wire  1 - instr_valid_o $end
     $var wire  1 - instr_valid_q $end
     $var wire  1 3 reset_ni $end
    $upscope $end
    $scope module ifu0 $end
     $var wire  1 2 clk_i $end
     $var wire  1 & cyc_q $end
     $var wire 32 ( instr_o [31:0] $end
     $var wire 32 ( instr_q [31:0] $end
     $var wire  1 * instr_ready_i $end
     $var wire  1 ) instr_valid_o $end
     $var wire  1 ) instr_valid_q $end
     $var wire  1 0 invalid_q $end
     $var wire 30 8 pc_i [29:0] $end
     $var wire 30 % pc_q [29:0] $end
     $var wire  1 + pc_valid_i $end
     $var wire  1 3 reset_ni $end
     $var wire  1 ' stb_q $end
     $var wire  1 $ wb_ack_i $end
     $var wire 30 % wb_addr_o [29:0] $end
     $var wire  1 & wb_cyc_o $end
     $var wire 32 # wb_data_i [31:0] $end
     $var wire 32 6 wb_data_o [31:0] $end
     $var wire  1 5 wb_err_i $end
     $var wire  4 7 wb_sel_o [3:0] $end
     $var wire  1 5 wb_stall_i $end
     $var wire  1 ' wb_stb_o $end
     $var wire  1 5 wb_we_o $end
    $upscope $end
   $upscope $end
   $scope module rom0 $end
    $var wire 32 = AddrWidth [31:0] $end
    $var wire 64 9 Contents [63:0] $end
    $var wire 32 < DataWidth [31:0] $end
    $var wire 32 ; Depth [31:0] $end
    $var wire 32 > SelWidth [31:0] $end
    $var wire  1 $ bus_ack $end
    $var wire 12 1 bus_addr [11:0] $end
    $var wire  1 & bus_cyc $end
    $var wire 32 6 bus_data_m [31:0] $end
    $var wire 32 # bus_data_s [31:0] $end
    $var wire  1 5 bus_err $end
    $var wire  4 7 bus_sel [3:0] $end
    $var wire  1 5 bus_stall $end
    $var wire  1 ' bus_stb $end
    $var wire  1 5 bus_we $end
    $var wire  1 2 clk $end
   $upscope $end
  $upscope $end
 $upscope $end
$enddefinitions $end


#0
b00000000000000000000000000000000 #
0$
b000000000000000000000000000000 %
0&
0'
b00000000000000000000000000000000 (
0)
1*
0+
b00000000000000000000000000000000 ,
0-
0.
b00000000000000000000000000000000 /
00
b000000000000 1
12
03
b0000 4
05
b00000000000000000000000000000000 6
b0000 7
b000000000000000000000000000001 8
b0111010001100101011100110111010000101110011011010110010101101101 9
b00000000000000000001000000000000 ;
b00000000000000000000000000100000 <
b00000000000000000000000000001100 =
b00000000000000000000000000000100 >
#1
02
#2
b00000000000000000001000100010001 #
1&
1'
b00000000000000000000000000000001 /
12
13
#3
02
#4
1$
0'
b00000000000000000000000000000010 /
12
#5
02
#6
0$
0&
b00000000000000000001000100010001 (
1)
b00000000000000000000000000000011 /
12
#7
02
#8
b000000000000000000000000000001 %
0)
0*
b00000000000000000001000100010001 ,
1-
b00000000000000000000000000000100 /
b000000000001 1
12
#9
02
#10
b00000000000000000010001000100010 #
1&
1'
b00000000000000000000000000000101 /
12
#11
02
#12
1$
0'
b00000000000000000000000000000110 /
12
#13
02
#14
0$
0&
b00000000000000000010001000100010 (
1)
b00000000000000000000000000000111 /
12
#15
02
#16
1.
b00000000000000000000000000001000 /
12
#17
02
#18
1*
0-
b00000000000000000000000000001001 /
12
#19
02
#20
b000000000000000000000000000010 %
0)
0*
b00000000000000000010001000100010 ,
1-
b00000000000000000000000000001010 /
b000000000010 1
12
#21
02
#22
b00000000000000000011001100110011 #
1&
1'
1*
0-
b00000000000000000000000000001011 /
12
#23
02
#24
1$
0'
b00000000000000000000000000001100 /
12
#25
02
#26
0$
0&
b00000000000000000011001100110011 (
1)
b00000000000000000000000000001101 /
12
#27
02
#28
b000000000000000000000000000011 %
0)
0*
b00000000000000000011001100110011 ,
1-
b00000000000000000000000000001110 /
b000000000011 1
12
#29
02
#30
b00000000000000000100010001000100 #
1&
1'
1*
0-
b00000000000000000000000000001111 /
12
#31
02
#32
1$
0'
b00000000000000000000000000010000 /
12
#33
02
#34
0$
0&
b00000000000000000100010001000100 (
1)
b00000000000000000000000000010001 /
12
#35
02
#36
b000000000000000000000000000100 %
0)
0*
b00000000000000000100010001000100 ,
1-
b00000000000000000000000000010010 /
b000000000100 1
12
#37
02
#38
b00000000000000000101010101010101 #
1&
1'
1*
0-
b00000000000000000000000000010011 /
12
#39
02
#40
1$
0'
b00000000000000000000000000010100 /
12
#41
02
#42
0$
0&
b00000000000000000101010101010101 (
1)
b00000000000000000000000000010101 /
12
#43
02
#44
b000000000000000000000000000101 %
0)
0*
b00000000000000000101010101010101 ,
1-
b00000000000000000000000000010110 /
b000000000101 1
12
#45
02
#46
b00000000000000000110011001100110 #
1&
1'
1*
0-
b00000000000000000000000000010111 /
12
#47
02
#48
1$
0'
b00000000000000000000000000011000 /
12
#49
02
#50
0$
0&
b00000000000000000110011001100110 (
1)
b00000000000000000000000000011001 /
12
#51
02
#52
b000000000000000000000000000110 %
0)
0*
b00000000000000000110011001100110 ,
1-
b00000000000000000000000000011010 /
b000000000110 1
12
#53
02
#54
b11011110101011011011111011101111 #
1&
1'
1*
0-
b00000000000000000000000000011011 /
12
#55
02
#56
1$
0'
b00000000000000000000000000011100 /
12
#57
02
#58
0$
0&
b11011110101011011011111011101111 (
1)
b00000000000000000000000000011101 /
12
#59
02
#60
b000000000000000000000000000111 %
0)
0*
b11011110101011011011111011101111 ,
1-
b00000000000000000000000000011110 /
b000000000111 1
12
#61
02
#62
b00000000000000000111011101110111 #
1&
1'
1*
1+
0-
b00000000000000000000000000011111 /
12
#63
02
#64
1$
b000000000000000000000000000001 %
0'
0+
b00000000000000000000000000100000 /
10
b000000000001 1
12
#65
02
#66
b00000000000000000010001000100010 #
0$
0&
b00000000000000000111011101110111 (
b00000000000000000000000000100001 /
12
#67
02
#68
1&
1'
b00000000000000000000000000100010 /
00
12
#69
02
#70
1$
0'
b00000000000000000000000000100011 /
12
#71
02
#72
0$
0&
b00000000000000000010001000100010 (
1)
b00000000000000000000000000100100 /
12
#73
02
#74
b000000000000000000000000000010 %
0)
0*
b00000000000000000010001000100010 ,
1-
b00000000000000000000000000100101 /
b000000000010 1
12
#75
02
#76
b00000000000000000011001100110011 #
1&
1'
1*
0-
b00000000000000000000000000100110 /
12
#77
02
#78
1$
0'
b00000000000000000000000000100111 /
12
#79
02
#80
0$
0&
b00000000000000000011001100110011 (
1)
b00000000000000000000000000101000 /
12
#81
02
#82
b000000000000000000000000000011 %
0)
0*
b00000000000000000011001100110011 ,
1-
b00000000000000000000000000101001 /
b000000000011 1
12
#83
02
#84
b00000000000000000100010001000100 #
1&
1'
1*
0-
b00000000000000000000000000101010 /
12
#85
02
#86
1$
0'
b00000000000000000000000000101011 /
12
#87
02
#88
0$
0&
b00000000000000000100010001000100 (
1)
b00000000000000000000000000101100 /
12
#89
02
#90
b000000000000000000000000000100 %
0)
0*
b00000000000000000100010001000100 ,
1-
b00000000000000000000000000101101 /
b000000000100 1
12
#91
02
#92
b00000000000000000101010101010101 #
1&
1'
1*
0-
b00000000000000000000000000101110 /
12
#93
02
#94
1$
0'
b00000000000000000000000000101111 /
12
#95
02
#96
0$
0&
b00000000000000000101010101010101 (
1)
b00000000000000000000000000110000 /
12
#97
02
#98
b000000000000000000000000000101 %
0)
0*
b00000000000000000101010101010101 ,
1-
b00000000000000000000000000110001 /
b000000000101 1
12
#99
02
#100
b00000000000000000110011001100110 #
1&
1'
1*
0-
b00000000000000000000000000110010 /
12
#101
02
#102
1$
0'
b00000000000000000000000000110011 /
12
#103
02
#104
0$
0&
b00000000000000000110011001100110 (
1)
b00000000000000000000000000110100 /
12
#105
02
#106
b000000000000000000000000000110 %
0)
0*
b00000000000000000110011001100110 ,
1-
b00000000000000000000000000110101 /
b000000000110 1
12
#107
02
#108
b11011110101011011011111011101111 #
1&
1'
1*
0-
b00000000000000000000000000110110 /
12
#109
02
#110
1$
0'
b00000000000000000000000000110111 /
12
#111
02
#112
0$
0&
b11011110101011011011111011101111 (
1)
b00000000000000000000000000111000 /
12
#113
02
#114
b000000000000000000000000000111 %
0)
0*
b11011110101011011011111011101111 ,
1-
b00000000000000000000000000111001 /
b000000000111 1
12
#115
02
#116
b00000000000000000111011101110111 #
1&
1'
1*
1+
0-
b00000000000000000000000000111010 /
12
#117
02
#118
1$
b000000000000000000000000000001 %
0'
0+
b00000000000000000000000000111011 /
10
b000000000001 1
12
#119
02
#120
b00000000000000000010001000100010 #
0$
0&
b00000000000000000111011101110111 (
b00000000000000000000000000111100 /
12
#121
02
#122
1&
1'
b00000000000000000000000000111101 /
00
12
#123
02
#124
1$
0'
b00000000000000000000000000111110 /
12
#125
02
#126
0$
0&
b00000000000000000010001000100010 (
1)
b00000000000000000000000000111111 /
12
#127
02
#128
b000000000000000000000000000010 %
0)
0*
b00000000000000000010001000100010 ,
1-
b00000000000000000000000001000000 /
b000000000010 1
12
#129
02
#130
b00000000000000000011001100110011 #
1&
1'
1*
0-
b00000000000000000000000001000001 /
12
#131
02
#132
1$
0'
b00000000000000000000000001000010 /
12
#133
02
#134
0$
0&
b00000000000000000011001100110011 (
1)
b00000000000000000000000001000011 /
12
#135
02
#136
b000000000000000000000000000011 %
0)
0*
b00000000000000000011001100110011 ,
1-
b00000000000000000000000001000100 /
b000000000011 1
12
#137
02
#138
b00000000000000000100010001000100 #
1&
1'
1*
0-
b00000000000000000000000001000101 /
12
#139
02
#140
1$
0'
b00000000000000000000000001000110 /
12
#141
02
#142
0$
0&
b00000000000000000100010001000100 (
1)
b00000000000000000000000001000111 /
12
#143
02
#144
b000000000000000000000000000100 %
0)
0*
b00000000000000000100010001000100 ,
1-
b00000000000000000000000001001000 /
b000000000100 1
12
#145
02
#146
b00000000000000000101010101010101 #
1&
1'
1*
0-
b00000000000000000000000001001001 /
12
#147
02
#148
1$
0'
b00000000000000000000000001001010 /
12
#149
02
#150
0$
0&
b00000000000000000101010101010101 (
1)
b00000000000000000000000001001011 /
12
#151
02
#152
b000000000000000000000000000101 %
0)
0*
b00000000000000000101010101010101 ,
1-
b00000000000000000000000001001100 /
b000000000101 1
12
#153
02
#154
b00000000000000000110011001100110 #
1&
1'
1*
0-
b00000000000000000000000001001101 /
12
#155
02
#156
1$
0'
b00000000000000000000000001001110 /
12
#157
02
#158
0$
0&
b00000000000000000110011001100110 (
1)
b00000000000000000000000001001111 /
12
#159
02
#160
b000000000000000000000000000110 %
0)
0*
b00000000000000000110011001100110 ,
1-
b00000000000000000000000001010000 /
b000000000110 1
12
#161
02
#162
b11011110101011011011111011101111 #
1&
1'
1*
0-
b00000000000000000000000001010001 /
12
#163
02
#164
1$
0'
b00000000000000000000000001010010 /
12
#165
02
#166
0$
0&
b11011110101011011011111011101111 (
1)
b00000000000000000000000001010011 /
12
#167
02
#168
b000000000000000000000000000111 %
0)
0*
b11011110101011011011111011101111 ,
1-
b00000000000000000000000001010100 /
b000000000111 1
12
#169
02
#170
b00000000000000000111011101110111 #
1&
1'
1*
1+
0-
b00000000000000000000000001010101 /
12
#171
02
#172
1$
b000000000000000000000000000001 %
0'
0+
b00000000000000000000000001010110 /
10
b000000000001 1
12
#173
02
#174
b00000000000000000010001000100010 #
0$
0&
b00000000000000000111011101110111 (
b00000000000000000000000001010111 /
12
#175
02
#176
1&
1'
b00000000000000000000000001011000 /
00
12
#177
02
#178
1$
0'
b00000000000000000000000001011001 /
12
#179
02
#180
0$
0&
b00000000000000000010001000100010 (
1)
b00000000000000000000000001011010 /
12
#181
02
#182
b000000000000000000000000000010 %
0)
0*
b00000000000000000010001000100010 ,
1-
b00000000000000000000000001011011 /
b000000000010 1
12
#183
02
#184
b00000000000000000011001100110011 #
1&
1'
1*
0-
b00000000000000000000000001011100 /
12
#185
02
#186
1$
0'
b00000000000000000000000001011101 /
12
#187
02
#188
0$
0&
b00000000000000000011001100110011 (
1)
b00000000000000000000000001011110 /
12
#189
02
#190
b000000000000000000000000000011 %
0)
0*
b00000000000000000011001100110011 ,
1-
b00000000000000000000000001011111 /
b000000000011 1
12
#191
02
#192
b00000000000000000100010001000100 #
1&
1'
1*
0-
b00000000000000000000000001100000 /
12
#193
02
#194
1$
0'
b00000000000000000000000001100001 /
12
#195
02
#196
0$
0&
b00000000000000000100010001000100 (
1)
b00000000000000000000000001100010 /
12
#197
02
#198
b000000000000000000000000000100 %
0)
0*
b00000000000000000100010001000100 ,
1-
b00000000000000000000000001100011 /
b000000000100 1
12
#199
02
#200
b00000000000000000101010101010101 #
1&
1'
1*
0-
b00000000000000000000000001100100 /
12
