rtl/riscv/riscv.sv
`default_nettype none

/* verilator lint_off DECLFILENAME */
/* verilator lint_off UNUSED */

// Instruction Fetch Unit
module riscv_ifu
(
  input wire logic clk_i,
  input wire logic reset_ni,

  // New PC (for jumps and branches)
  // This will invalidate any currently processing instructions
  input wire logic pc_valid_i,
  input wire logic [29:0] pc_i,

  // Interface to IDU
  input wire logic instr_ready_i, //TODO rename to ready_i ?
  output logic instr_valid_o, //TODO rename to valid_o ?
  output logic [31:0] instr_o,
  output logic [29:0] pc_o,

  // Master port
  input wire logic wb_ack_i,
  input wire logic wb_stall_i,
  input wire logic wb_err_i,
  input wire logic [31:0] wb_data_i,
  output logic [31:0] wb_data_o,
  output logic [29:0] wb_addr_o,
  output logic [3:0] wb_sel_o,
  output logic wb_cyc_o,
  output logic wb_stb_o,
  output logic wb_we_o
);

logic [29:0] pc_q;
logic [31:0] instr_q;
logic instr_valid_q;
logic cyc_q;
logic stb_q;
logic invalid_q; // Skip next ack

assign wb_sel_o = '0;
assign wb_data_o = '0;
assign wb_we_o = '0;

assign instr_o = instr_q;
assign instr_valid_o = instr_valid_q;
assign wb_cyc_o = cyc_q;
assign wb_stb_o = stb_q;
assign wb_addr_o = pc_q;

initial pc_q = '0;
initial instr_valid_q = '0;
initial cyc_q = '0;
initial stb_q = '0;
initial invalid_q = '0;

always_ff @(posedge clk_i) begin
  if((!reset_ni) || (!cyc_q) ) begin
    invalid_q <= '0;
  end else if(pc_valid_i) begin
    invalid_q <= '1;
  end
end

always_ff @(posedge clk_i) begin
  if((!reset_ni) || (cyc_q && wb_ack_i)) begin
    cyc_q <= '0;
    stb_q <= '0;
  end else if(!cyc_q && (!instr_valid_o)) begin
    cyc_q <= '1;
    stb_q <= '1;
  end else if(cyc_q) begin
    cyc_q <= '1;
    if(!wb_stall_i) begin
      stb_q <= '0;
    end
  end
end

always_ff @(posedge clk_i) begin
  if(wb_cyc_o && wb_ack_i) begin
    instr_q <= wb_data_i;
    pc_o <= pc_q;
  end
end

always_ff @(posedge clk_i) begin
  if(pc_valid_i) begin
    pc_q <= pc_i;
  end else if(instr_valid_q && instr_ready_i) begin
    pc_q <= pc_q + 1'b1;
  end
end

always_ff @(posedge clk_i) begin
  if((!reset_ni) || pc_valid_i) begin
    instr_valid_q <= '0;
  end else if(wb_cyc_o && wb_ack_i && !invalid_q) begin
    instr_valid_q <= '1;
  end else if(instr_ready_i) begin
    instr_valid_q <= '0;
  end
end

endmodule


module riscv_regfile
(
  input wire logic clk_i,

  // write port
  input wire logic [31:0] w_data_i,
  input wire logic [4:0] w_addr_i,
  input wire logic w_enable_i,

  // read port 0
  input wire logic [4:0] rd0_addr_i,
  output logic [31:0] rd0_data_o,

  // read port 1
  input wire logic [4:0] rd1_addr_i,
  output logic [31:0] rd1_data_o
);

logic [31:0] regs[32];

initial begin
  for(int i = 0; i < Count; i+= 1) begin
    regs[i] = '0;
  end
end

always_comb begin
  rd0_data_o = regs[rd0_addr_i];
  rd1_data_o = regs[rd1_addr_i];
end

always_ff @(posedge clk_i) begin
  if(w_enable_i && w_addr_i != '0) begin
    regs[w_addr_i] <= w_data_i;
  end
end

endmodule;


// Instruction Decode Unit
module riscv_idu
(
  input wire logic clk_i,
  input wire logic reset_ni,

  input wire logic clear_i, // Branch Clear
  input wire logic stall_i, // Hazard stall

  // IFU interface
  output logic ready_o,
  input wire logic valid_i,
  input wire logic [31:0] instr_i,
  input wire logic [29:0] pc_i,

  // EXU interface
  input wire logic ready_i,
  output logic valid_o,

  output [29:0] pc_o,

  output [4:0] rd_addr_o,

  // alu
  output alu_cmd_t alu_cmd_o,
  output logic [31:0] alu_lhs_o,
  output logic [31:0] alu_rhs_o,

  // branch
  output branch_alu_cmd_t branch_cmd_o,
  output logic [31:0] branch_lhs_o,
  output logic [31:0] branch_rhs_o,

  output logic branch_o, // Perform a jump or branch

  //TODO y'know, signals

  // Regfile interface
  output logic [4:0] rf_rd0_addr_o,
  output logic [4:0] rf_rd1_addr_o,
  input wire logic [31:0] rf_rd0_data_i,
  input wire logic [31:0] rf_rd0_data_i
);

logic [6:0] opcode;
logic [4:0] rd;
logic [2:0] funct3;
logic [4:0] rs1;
logic [4:0] rs2;
logic [6:0] funct7;

logic [31:0] i_imm;
logic [31:0] s_imm;
logic [31:0] b_imm;
logic [31:0] u_imm;
logic [31:0] j_imm;

logic branch_cmd_d;

initial ready_o = '1; //TODO probably needs to be combinatorical
initial valid_o = '0;

always_comb begin
  opcode = instr_i[6:0];
  rd = instr_i[11:7];
  funct3 = instr_i[14:12];
  rs1 = instr_i[19:15];
  rs2 = instr_i[24:20];
  funct7 = instr_i[31:25];

  i_imm = { {20{instr_i[31]}} , instr_i[31:20] };
  s_imm = { {20{instr_i[31]}}, instr_i[31:25], instr_i[11:7] };
  b_imm = { {19{instr_i[31]}}, instr_i[31], instr_i[7], instr_i[30:25], instr_i[11:8], 1'b0 };
  u_imm = { instr_i[31:12], 12'b0 };
  j_imm = { {12{instr_i[31]}}, instr_i[19:12], instr_i[20], instr_i[30:21], 1'b0 };

  unique case (funct3)
    3'b000: branch_cmd_d = Eq;
    3'b001: branch_cmd_d = Ne;
    3'b100: branch_cmd_d = Lt;
    3'b101: branch_cmd_d = Ge;
    3'b110: branch_cmd_d = Ltu;
    3'b111: branch_cmd_d = Geu;
    default: branch_cmd_d = Eq;
  endcase
end

endmodule


module riscv_dummy
(
  input wire logic clk_i,
  input wire logic reset_ni,

  input wire logic clear_i,

  input wire logic [31:0] instr_i,
  input wire logic instr_valid_i,
  output logic instr_ready_o,

  output logic [31:0] instr_o,
  output logic instr_valid_o,
  input wire logic instr_ready_i
);

logic [31:0] instr_q;
logic instr_valid_q;
logic instr_ready_q;

initial instr_valid_q = '0;
initial instr_ready_q = '1;

assign instr_o = instr_q;
assign instr_valid_o = instr_valid_q;
assign instr_ready_o = instr_ready_q;

always_ff @(posedge clk_i) begin
  if((!reset_ni) || clear_i) begin
    instr_valid_q <= '0;
    instr_ready_q <= '1;
  end else if(instr_valid_i && !instr_valid_o) begin
    instr_q <= instr_i;
    instr_valid_q <= '1;
    instr_ready_q <= '0;
  end else if(instr_valid_q && instr_ready_i) begin
    instr_valid_q <= '0;
    instr_ready_q <= '1;
  end

  //instr_ready_q <= instr_ready_i;
end

endmodule

module riscv_dummy_branch
(
  input wire logic clk_i,
  input wire logic reset_ni,

  input wire logic [31:0] instr_i,
  input wire logic instr_valid_i,
  output logic instr_ready_o,

  output logic pc_valid_o
);

logic [31:0] timer;
initial timer = '0;
always_ff @(posedge clk_i) begin
  timer <= timer + 1;
end

initial pc_valid_o = '0;

assign instr_ready_o = timer >= 8 ? '1 : '0;

always_ff @(posedge clk_i) begin
  if(!reset_ni) begin
    pc_valid_o <= '0;
  end else begin
    if(instr_valid_i && instr_i == 32'hDEADBEEF) begin
      pc_valid_o <= '1;
    end else begin
      pc_valid_o <= '0;
    end
  end
end

endmodule

module riscv
(
  input wire logic clk_i,
  input wire logic reset_ni,

  // Instruction Port
  input wire logic wb_i_ack_i,
  input wire logic wb_i_stall_i,
  input wire logic wb_i_err_i,
  input wire logic [31:0] wb_i_data_i,
  output logic [31:0] wb_i_data_o,
  output logic [29:0] wb_i_addr_o,
  output logic [3:0] wb_i_sel_o,
  output logic wb_i_cyc_o,
  output logic wb_i_stb_o,
  output logic wb_i_we_o
);

logic [31:0] ifu_instr;
logic ifu_valid;
logic ifu_ready;

logic ifu_pc_valid;

logic [31:0] dummy_instr;
logic dummy_valid;
logic dummy_ready;

riscv_dummy dummy0
(
  .clk_i,
  .reset_ni,

  .clear_i(ifu_pc_valid),

  .instr_i(ifu_instr),
  .instr_valid_i(ifu_valid),
  .instr_ready_o(ifu_ready),

  .instr_valid_o(dummy_valid),
  .instr_o(dummy_instr),
  .instr_ready_i(dummy_ready)
);

riscv_dummy_branch branch0
(
  .clk_i,
  .reset_ni,

  .instr_i(dummy_instr),
  .instr_valid_i(dummy_valid),
  .instr_ready_o(dummy_ready),

  .pc_valid_o(ifu_pc_valid)
);

riscv_ifu ifu0
(
  .clk_i,
  .reset_ni,

  // Tie ready to high
  .instr_ready_i(ifu_ready),
  .instr_valid_o(ifu_valid),
  .instr_o(ifu_instr),

  .pc_i(1),
  .pc_valid_i(ifu_pc_valid),

  .wb_ack_i(wb_i_ack_i),
  .wb_stall_i(wb_i_stall_i),
  .wb_err_i(wb_i_err_i),
  .wb_data_i(wb_i_data_i),
  .wb_data_o(wb_i_data_o),
  .wb_addr_o(wb_i_addr_o),
  .wb_sel_o(wb_i_sel_o),
  .wb_cyc_o(wb_i_cyc_o),
  .wb_stb_o(wb_i_stb_o),
  .wb_we_o(wb_i_we_o)
);

endmodule

rtl/rom.sv
`default_nettype none

/* verilator lint_off UNUSED */

module rom
#(
  parameter Contents = "",
  parameter Depth = 0,

  localparam DataWidth = 32,
  localparam AddrWidth = $clog2(Depth),
  localparam SelWidth = DataWidth / 8
)
(
  input wire logic clk,

  output logic [DataWidth-1:0] bus_data_s,
  output logic bus_ack,
  output logic bus_stall,
  output logic bus_err,

  input wire logic [DataWidth-1:0] bus_data_m,
  input wire logic [AddrWidth-1:0] bus_addr,
  input wire logic [SelWidth-1:0] bus_sel,
  input wire logic bus_cyc,
  input wire logic bus_stb,
  input wire logic bus_we
);

logic [DataWidth-1:0] mem [0:Depth-1];

initial begin
  bus_ack = '0;

  $readmemh(Contents, mem);
end

assign bus_err = '0;
assign bus_stall = '0;

always_ff @(posedge clk) begin
  bus_data_s <= mem[bus_addr];
  bus_ack <= bus_stb;
end

endmodule

rtl/sim/riscv_top.sv
`default_nettype none

/* verilator lint_off UNUSED */

module riscv_top
(
  input wire logic clk_i,
  input wire logic reset_ni,
  output logic [3:0] leds_o
);

// Rom
logic [31:0] rom_data_s;
logic rom_ack;
logic rom_stall;
logic rom_err;
logic [31:0] rom_data_m;
logic [29:0] rom_addr;
logic [3:0] rom_sel;
logic rom_cyc;
logic rom_stb;
logic rom_we;

assign leds_o = '0;

rom
#(
  .Contents("test.mem"),
  .Depth(4096) //16 Kilobytes
) rom0
(
  .clk(clk_i),

  .bus_data_s(rom_data_s),
  .bus_ack(rom_ack),
  .bus_stall(rom_stall),
  .bus_err(rom_err),
  .bus_data_m(rom_data_m),
  .bus_addr(rom_addr[11:0]),
  .bus_sel(rom_sel),
  .bus_cyc(rom_cyc),
  .bus_stb(rom_stb),
  .bus_we(rom_we)
);

riscv cpu0
(
  .clk_i,
  .reset_ni,

  .wb_i_data_i(rom_data_s),
  .wb_i_ack_i(rom_ack),
  .wb_i_stall_i(rom_stall),
  .wb_i_err_i(rom_err),
  .wb_i_data_o(rom_data_m),
  .wb_i_addr_o(rom_addr),
  .wb_i_sel_o(rom_sel),
  .wb_i_cyc_o(rom_cyc),
  .wb_i_stb_o(rom_stb),
  .wb_i_we_o(rom_we)
);

endmodule

sim/riscv/trace.vcd
$version Generated by VerilatedVcd $end
$date Sat Nov 12 14:57:46 2022 $end
$timescale 1ps $end

 $scope module TOP $end
  $var wire  1 3 clk_i $end
  $var wire  4 5 leds_o [3:0] $end
  $var wire  1 4 reset_ni $end
  $scope module riscv_top $end
   $var wire  1 3 clk_i $end
   $var wire  4 5 leds_o [3:0] $end
   $var wire  1 4 reset_ni $end
   $var wire  1 $ rom_ack $end
   $var wire 30 % rom_addr [29:0] $end
   $var wire  1 & rom_cyc $end
   $var wire 32 7 rom_data_m [31:0] $end
   $var wire 32 # rom_data_s [31:0] $end
   $var wire  1 6 rom_err $end
   $var wire  4 8 rom_sel [3:0] $end
   $var wire  1 6 rom_stall $end
   $var wire  1 ' rom_stb $end
   $var wire  1 6 rom_we $end
   $scope module cpu0 $end
    $var wire  1 3 clk_i $end
    $var wire 32 , dummy_instr [31:0] $end
    $var wire  1 . dummy_ready $end
    $var wire  1 - dummy_valid $end
    $var wire 32 ( ifu_instr [31:0] $end
    $var wire  1 + ifu_pc_valid $end
    $var wire  1 * ifu_ready $end
    $var wire  1 ) ifu_valid $end
    $var wire  1 4 reset_ni $end
    $var wire  1 $ wb_i_ack_i $end
    $var wire 30 % wb_i_addr_o [29:0] $end
    $var wire  1 & wb_i_cyc_o $end
    $var wire 32 # wb_i_data_i [31:0] $end
    $var wire 32 7 wb_i_data_o [31:0] $end
    $var wire  1 6 wb_i_err_i $end
    $var wire  4 8 wb_i_sel_o [3:0] $end
    $var wire  1 6 wb_i_stall_i $end
    $var wire  1 ' wb_i_stb_o $end
    $var wire  1 6 wb_i_we_o $end
    $scope module branch0 $end
     $var wire  1 3 clk_i $end
     $var wire 32 , instr_i [31:0] $end
     $var wire  1 . instr_ready_o $end
     $var wire  1 - instr_valid_i $end
     $var wire  1 + pc_valid_o $end
     $var wire  1 4 reset_ni $end
     $var wire 32 / timer [31:0] $end
    $upscope $end
    $scope module dummy0 $end
     $var wire  1 + clear_i $end
     $var wire  1 3 clk_i $end
     $var wire 32 ( instr_i [31:0] $end
     $var wire 32 , instr_o [31:0] $end
     $var wire 32 , instr_q [31:0] $end
     $var wire  1 . instr_ready_i $end
     $var wire  1 * instr_ready_o $end
     $var wire  1 * instr_ready_q $end
     $var wire  1 ) instr_valid_i $end
     $var wire  1 - instr_valid_o $end
     $var wire  1 - instr_valid_q $end
     $var wire  1 4 reset_ni $end
    $upscope $end
    $scope module ifu0 $end
     $var wire  1 3 clk_i $end
     $var wire  1 & cyc_q $end
     $var wire 32 ( instr_o [31:0] $end
     $var wire 32 ( instr_q [31:0] $end
     $var wire  1 * instr_ready_i $end
     $var wire  1 ) instr_valid_o $end
     $var wire  1 ) instr_valid_q $end
     $var wire  1 1 invalid_q $end
     $var wire 30 9 pc_i [29:0] $end
     $var wire 30 0 pc_o [29:0] $end
     $var wire 30 % pc_q [29:0] $end
     $var wire  1 + pc_valid_i $end
     $var wire  1 4 reset_ni $end
     $var wire  1 ' stb_q $end
     $var wire  1 $ wb_ack_i $end
     $var wire 30 % wb_addr_o [29:0] $end
     $var wire  1 & wb_cyc_o $end
     $var wire 32 # wb_data_i [31:0] $end
     $var wire 32 7 wb_data_o [31:0] $end
     $var wire  1 6 wb_err_i $end
     $var wire  4 8 wb_sel_o [3:0] $end
     $var wire  1 6 wb_stall_i $end
     $var wire  1 ' wb_stb_o $end
     $var wire  1 6 wb_we_o $end
    $upscope $end
   $upscope $end
   $scope module rom0 $end
    $var wire 32 > AddrWidth [31:0] $end
    $var wire 64 : Contents [63:0] $end
    $var wire 32 = DataWidth [31:0] $end
    $var wire 32 < Depth [31:0] $end
    $var wire 32 ? SelWidth [31:0] $end
    $var wire  1 $ bus_ack $end
    $var wire 12 2 bus_addr [11:0] $end
    $var wire  1 & bus_cyc $end
    $var wire 32 7 bus_data_m [31:0] $end
    $var wire 32 # bus_data_s [31:0] $end
    $var wire  1 6 bus_err $end
    $var wire  4 8 bus_sel [3:0] $end
    $var wire  1 6 bus_stall $end
    $var wire  1 ' bus_stb $end
    $var wire  1 6 bus_we $end
    $var wire  1 3 clk $end
   $upscope $end
  $upscope $end
 $upscope $end
$enddefinitions $end


#0
b00000000000000000000000000000000 #
0$
b000000000000000000000000000000 %
0&
0'
b00000000000000000000000000000000 (
0)
1*
0+
b00000000000000000000000000000000 ,
0-
0.
b00000000000000000000000000000000 /
b000000000000000000000000000000 0
01
b000000000000 2
13
04
b0000 5
06
b00000000000000000000000000000000 7
b0000 8
b000000000000000000000000000001 9
b0111010001100101011100110111010000101110011011010110010101101101 :
b00000000000000000001000000000000 <
b00000000000000000000000000100000 =
b00000000000000000000000000001100 >
b00000000000000000000000000000100 ?
#1
03
#2
1&
1'
b00000000000000000000000000000001 /
13
14
#3
03
#4
b00000000000000000001000100010001 #
1$
0'
b00000000000000000000000000000010 /
13
#5
03
#6
b00000000000000000000000000000000 #
0$
0&
b00000000000000000001000100010001 (
1)
b00000000000000000000000000000011 /
13
#7
03
#8
b000000000000000000000000000001 %
0)
0*
b00000000000000000001000100010001 ,
1-
b00000000000000000000000000000100 /
b000000000001 2
13
#9
03
#10
1&
1'
b00000000000000000000000000000101 /
13
#11
03
#12
b00000000000000000010001000100010 #
1$
0'
b00000000000000000000000000000110 /
13
#13
03
#14
b00000000000000000000000000000000 #
0$
0&
b00000000000000000010001000100010 (
1)
b00000000000000000000000000000111 /
b000000000000000000000000000001 0
13
#15
03
#16
1.
b00000000000000000000000000001000 /
13
#17
03
#18
1*
0-
b00000000000000000000000000001001 /
13
#19
03
#20
b000000000000000000000000000010 %
0)
0*
b00000000000000000010001000100010 ,
1-
b00000000000000000000000000001010 /
b000000000010 2
13
#21
03
#22
1&
1'
1*
0-
b00000000000000000000000000001011 /
13
#23
03
#24
b00000000000000000011001100110011 #
1$
0'
b00000000000000000000000000001100 /
13
#25
03
#26
b00000000000000000000000000000000 #
0$
0&
b00000000000000000011001100110011 (
1)
b00000000000000000000000000001101 /
b000000000000000000000000000010 0
13
#27
03
#28
b000000000000000000000000000011 %
0)
0*
b00000000000000000011001100110011 ,
1-
b00000000000000000000000000001110 /
b000000000011 2
13
#29
03
#30
1&
1'
1*
0-
b00000000000000000000000000001111 /
13
#31
03
#32
b00000000000000000100010001000100 #
1$
0'
b00000000000000000000000000010000 /
13
#33
03
#34
b00000000000000000000000000000000 #
0$
0&
b00000000000000000100010001000100 (
1)
b00000000000000000000000000010001 /
b000000000000000000000000000011 0
13
#35
03
#36
b000000000000000000000000000100 %
0)
0*
b00000000000000000100010001000100 ,
1-
b00000000000000000000000000010010 /
b000000000100 2
13
#37
03
#38
1&
1'
1*
0-
b00000000000000000000000000010011 /
13
#39
03
#40
b00000000000000000101010101010101 #
1$
0'
b00000000000000000000000000010100 /
13
#41
03
#42
b00000000000000000000000000000000 #
0$
0&
b00000000000000000101010101010101 (
1)
b00000000000000000000000000010101 /
b000000000000000000000000000100 0
13
#43
03
#44
b000000000000000000000000000101 %
0)
0*
b00000000000000000101010101010101 ,
1-
b00000000000000000000000000010110 /
b000000000101 2
13
#45
03
#46
1&
1'
1*
0-
b00000000000000000000000000010111 /
13
#47
03
#48
b00000000000000000110011001100110 #
1$
0'
b00000000000000000000000000011000 /
13
#49
03
#50
b00000000000000000000000000000000 #
0$
0&
b00000000000000000110011001100110 (
1)
b00000000000000000000000000011001 /
b000000000000000000000000000101 0
13
#51
03
#52
b000000000000000000000000000110 %
0)
0*
b00000000000000000110011001100110 ,
1-
b00000000000000000000000000011010 /
b000000000110 2
13
#53
03
#54
1&
1'
1*
0-
b00000000000000000000000000011011 /
13
#55
03
#56
b11011110101011011011111011101111 #
1$
0'
b00000000000000000000000000011100 /
13
#57
03
#58
b00000000000000000000000000000000 #
0$
0&
b11011110101011011011111011101111 (
1)
b00000000000000000000000000011101 /
b000000000000000000000000000110 0
13
#59
03
#60
b000000000000000000000000000111 %
0)
0*
b11011110101011011011111011101111 ,
1-
b00000000000000000000000000011110 /
b000000000111 2
13
#61
03
#62
1&
1'
1*
1+
0-
b00000000000000000000000000011111 /
13
#63
03
#64
b00000000000000000111011101110111 #
1$
b000000000000000000000000000001 %
0'
0+
b00000000000000000000000000100000 /
11
b000000000001 2
13
#65
03
#66
b00000000000000000000000000000000 #
0$
0&
b00000000000000000111011101110111 (
b00000000000000000000000000100001 /
b000000000000000000000000000001 0
13
#67
03
#68
1&
1'
b00000000000000000000000000100010 /
01
13
#69
03
#70
b00000000000000000010001000100010 #
1$
0'
b00000000000000000000000000100011 /
13
#71
03
#72
b00000000000000000000000000000000 #
0$
0&
b00000000000000000010001000100010 (
1)
b00000000000000000000000000100100 /
13
#73
03
#74
b000000000000000000000000000010 %
0)
0*
b00000000000000000010001000100010 ,
1-
b00000000000000000000000000100101 /
b000000000010 2
13
#75
03
#76
1&
1'
1*
0-
b00000000000000000000000000100110 /
13
#77
03
#78
b00000000000000000011001100110011 #
1$
0'
b00000000000000000000000000100111 /
13
#79
03
#80
b00000000000000000000000000000000 #
0$
0&
b00000000000000000011001100110011 (
1)
b00000000000000000000000000101000 /
b000000000000000000000000000010 0
13
#81
03
#82
b000000000000000000000000000011 %
0)
0*
b00000000000000000011001100110011 ,
1-
b00000000000000000000000000101001 /
b000000000011 2
13
#83
03
#84
1&
1'
1*
0-
b00000000000000000000000000101010 /
13
#85
03
#86
b00000000000000000100010001000100 #
1$
0'
b00000000000000000000000000101011 /
13
#87
03
#88
b00000000000000000000000000000000 #
0$
0&
b00000000000000000100010001000100 (
1)
b00000000000000000000000000101100 /
b000000000000000000000000000011 0
13
#89
03
#90
b000000000000000000000000000100 %
0)
0*
b00000000000000000100010001000100 ,
1-
b00000000000000000000000000101101 /
b000000000100 2
13
#91
03
#92
1&
1'
1*
0-
b00000000000000000000000000101110 /
13
#93
03
#94
b00000000000000000101010101010101 #
1$
0'
b00000000000000000000000000101111 /
13
#95
03
#96
b00000000000000000000000000000000 #
0$
0&
b00000000000000000101010101010101 (
1)
b00000000000000000000000000110000 /
b000000000000000000000000000100 0
13
#97
03
#98
b000000000000000000000000000101 %
0)
0*
b00000000000000000101010101010101 ,
1-
b00000000000000000000000000110001 /
b000000000101 2
13
#99
03
#100
1&
1'
1*
0-
b00000000000000000000000000110010 /
13
#101
03
#102
b00000000000000000110011001100110 #
1$
0'
b00000000000000000000000000110011 /
13
#103
03
#104
b00000000000000000000000000000000 #
0$
0&
b00000000000000000110011001100110 (
1)
b00000000000000000000000000110100 /
b000000000000000000000000000101 0
13
#105
03
#106
b000000000000000000000000000110 %
0)
0*
b00000000000000000110011001100110 ,
1-
b00000000000000000000000000110101 /
b000000000110 2
13
#107
03
#108
1&
1'
1*
0-
b00000000000000000000000000110110 /
13
#109
03
#110
b11011110101011011011111011101111 #
1$
0'
b00000000000000000000000000110111 /
13
#111
03
#112
b00000000000000000000000000000000 #
0$
0&
b11011110101011011011111011101111 (
1)
b00000000000000000000000000111000 /
b000000000000000000000000000110 0
13
#113
03
#114
b000000000000000000000000000111 %
0)
0*
b11011110101011011011111011101111 ,
1-
b00000000000000000000000000111001 /
b000000000111 2
13
#115
03
#116
1&
1'
1*
1+
0-
b00000000000000000000000000111010 /
13
#117
03
#118
b00000000000000000111011101110111 #
1$
b000000000000000000000000000001 %
0'
0+
b00000000000000000000000000111011 /
11
b000000000001 2
13
#119
03
#120
b00000000000000000000000000000000 #
0$
0&
b00000000000000000111011101110111 (
b00000000000000000000000000111100 /
b000000000000000000000000000001 0
13
#121
03
#122
1&
1'
b00000000000000000000000000111101 /
01
13
#123
03
#124
b00000000000000000010001000100010 #
1$
0'
b00000000000000000000000000111110 /
13
#125
03
#126
b00000000000000000000000000000000 #
0$
0&
b00000000000000000010001000100010 (
1)
b00000000000000000000000000111111 /
13
#127
03
#128
b000000000000000000000000000010 %
0)
0*
b00000000000000000010001000100010 ,
1-
b00000000000000000000000001000000 /
b000000000010 2
13
#129
03
#130
1&
1'
1*
0-
b00000000000000000000000001000001 /
13
#131
03
#132
b00000000000000000011001100110011 #
1$
0'
b00000000000000000000000001000010 /
13
#133
03
#134
b00000000000000000000000000000000 #
0$
0&
b00000000000000000011001100110011 (
1)
b00000000000000000000000001000011 /
b000000000000000000000000000010 0
13
#135
03
#136
b000000000000000000000000000011 %
0)
0*
b00000000000000000011001100110011 ,
1-
b00000000000000000000000001000100 /
b000000000011 2
13
#137
03
#138
1&
1'
1*
0-
b00000000000000000000000001000101 /
13
#139
03
#140
b00000000000000000100010001000100 #
1$
0'
b00000000000000000000000001000110 /
13
#141
03
#142
b00000000000000000000000000000000 #
0$
0&
b00000000000000000100010001000100 (
1)
b00000000000000000000000001000111 /
b000000000000000000000000000011 0
13
#143
03
#144
b000000000000000000000000000100 %
0)
0*
b00000000000000000100010001000100 ,
1-
b00000000000000000000000001001000 /
b000000000100 2
13
#145
03
#146
1&
1'
1*
0-
b00000000000000000000000001001001 /
13
#147
03
#148
b00000000000000000101010101010101 #
1$
0'
b00000000000000000000000001001010 /
13
#149
03
#150
b00000000000000000000000000000000 #
0$
0&
b00000000000000000101010101010101 (
1)
b00000000000000000000000001001011 /
b000000000000000000000000000100 0
13
#151
03
#152
b000000000000000000000000000101 %
0)
0*
b00000000000000000101010101010101 ,
1-
b00000000000000000000000001001100 /
b000000000101 2
13
#153
03
#154
1&
1'
1*
0-
b00000000000000000000000001001101 /
13
#155
03
#156
b00000000000000000110011001100110 #
1$
0'
b00000000000000000000000001001110 /
13
#157
03
#158
b00000000000000000000000000000000 #
0$
0&
b00000000000000000110011001100110 (
1)
b00000000000000000000000001001111 /
b000000000000000000000000000101 0
13
#159
03
#160
b000000000000000000000000000110 %
0)
0*
b00000000000000000110011001100110 ,
1-
b00000000000000000000000001010000 /
b000000000110 2
13
#161
03
#162
1&
1'
1*
0-
b00000000000000000000000001010001 /
13
#163
03
#164
b11011110101011011011111011101111 #
1$
0'
b00000000000000000000000001010010 /
13
#165
03
#166
b00000000000000000000000000000000 #
0$
0&
b11011110101011011011111011101111 (
1)
b00000000000000000000000001010011 /
b000000000000000000000000000110 0
13
#167
03
#168
b000000000000000000000000000111 %
0)
0*
b11011110101011011011111011101111 ,
1-
b00000000000000000000000001010100 /
b000000000111 2
13
#169
03
#170
1&
1'
1*
1+
0-
b00000000000000000000000001010101 /
13
#171
03
#172
b00000000000000000111011101110111 #
1$
b000000000000000000000000000001 %
0'
0+
b00000000000000000000000001010110 /
11
b000000000001 2
13
#173
03
#174
b00000000000000000000000000000000 #
0$
0&
b00000000000000000111011101110111 (
b00000000000000000000000001010111 /
b000000000000000000000000000001 0
13
#175
03
#176
1&
1'
b00000000000000000000000001011000 /
01
13
#177
03
#178
b00000000000000000010001000100010 #
1$
0'
b00000000000000000000000001011001 /
13
#179
03
#180
b00000000000000000000000000000000 #
0$
0&
b00000000000000000010001000100010 (
1)
b00000000000000000000000001011010 /
13
#181
03
#182
b000000000000000000000000000010 %
0)
0*
b00000000000000000010001000100010 ,
1-
b00000000000000000000000001011011 /
b000000000010 2
13
#183
03
#184
1&
1'
1*
0-
b00000000000000000000000001011100 /
13
#185
03
#186
b00000000000000000011001100110011 #
1$
0'
b00000000000000000000000001011101 /
13
#187
03
#188
b00000000000000000000000000000000 #
0$
0&
b00000000000000000011001100110011 (
1)
b00000000000000000000000001011110 /
b000000000000000000000000000010 0
13
#189
03
#190
b000000000000000000000000000011 %
0)
0*
b00000000000000000011001100110011 ,
1-
b00000000000000000000000001011111 /
b000000000011 2
13
#191
03
#192
1&
1'
1*
0-
b00000000000000000000000001100000 /
13
#193
03
#194
b00000000000000000100010001000100 #
1$
0'
b00000000000000000000000001100001 /
13
#195
03
#196
b00000000000000000000000000000000 #
0$
0&
b00000000000000000100010001000100 (
1)
b00000000000000000000000001100010 /
b000000000000000000000000000011 0
13
#197
03
#198
b000000000000000000000000000100 %
0)
0*
b00000000000000000100010001000100 ,
1-
b00000000000000000000000001100011 /
b000000000100 2
13
#199
03
#200
1&
1'
1*
0-
b00000000000000000000000001100100 /
13
