rtl/led_interface.sv
`default_nettype none

module led_interface(
  input wire logic clk,
  input wire logic reset_n,

  input wire logic write_req,
  input wire logic [31:0] write_data,
  input wire logic [3:0] byte_enable,

  input wire logic read_req,
  output wire logic [31:0] read_data,
  output logic read_data_valid,

  output logic [3:0] leds);

logic read_data_valid_next;
logic [3:0] leds_next;

assign read_data = {28'h0, leds};

always_comb begin
  read_data_valid_next = read_data_valid;
  leds_next = leds;

  read_data_valid_next = read_req;
  if (write_req && byte_enable[0]) begin
    leds_next = write_data[3:0];
  end
end

always_ff @(posedge clk) begin
  if(!reset_n) begin
    read_data_valid <= 1'h0;
    leds <= 4'h0;
  end else begin
    read_data_valid <= read_data_valid_next;
    leds <= leds_next;
  end
end

endmodule

rtl/sim/led_interface_top.sv
`default_nettype none

module led_interface_top(
  input wire logic clk,
  input wire logic reset_n,

  output wire logic [3:0] leds
);

logic [31:0] counter;
logic [31:0] counter_next;

logic write_req;
logic [31:0] write_data;

logic read_req;

led_interface led0(
  .clk(clk),
  .reset_n(reset_n),
  .write_req(1),
  .write_data({28'h0, counter[24:21]}),
  .byte_enable(4'h1),
  .read_req(0),
  .leds(leds)
);

always_comb begin
  counter_next = counter + 1;
end

always_ff @(posedge clk) begin
  counter <= counter_next;
end

endmodule

sim/led_interface/test.vcd
$version Generated by VerilatedVcd $end
$date Mon Oct 24 22:33:00 2022 $end
$timescale 1ps $end

 $scope module TOP $end
  $var wire  1 ( clk $end
  $var wire  4 * leds [3:0] $end
  $var wire  1 ) reset_n $end
  $scope module led_interface_top $end
   $var wire  1 ( clk $end
   $var wire 32 # counter [31:0] $end
   $var wire 32 $ counter_next [31:0] $end
   $var wire  4 * leds [3:0] $end
   $var wire  1 . read_req $end
   $var wire  1 ) reset_n $end
   $var wire 32 - write_data [31:0] $end
   $var wire  1 , write_req $end
   $scope module led0 $end
    $var wire  4 0 byte_enable [3:0] $end
    $var wire  1 ( clk $end
    $var wire  4 * leds [3:0] $end
    $var wire  4 ' leds_next [3:0] $end
    $var wire 32 + read_data [31:0] $end
    $var wire  1 & read_data_valid $end
    $var wire  1 1 read_data_valid_next $end
    $var wire  1 1 read_req $end
    $var wire  1 ) reset_n $end
    $var wire 32 % write_data [31:0] $end
    $var wire  1 / write_req $end
   $upscope $end
  $upscope $end
 $upscope $end
$enddefinitions $end


#0
b00000000000000000000000000000000 #
b00000000000000000000000000000001 $
b00000000000000000000000000000000 %
0&
b0000 '
0(
0)
b0000 *
b00000000000000000000000000000000 +
0,
b00000000000000000000000000000000 -
0.
1/
b0001 0
01
#1
1)
#2
b00000000000000000000000000000001 #
b00000000000000000000000000000010 $
1(
#3
0(
#4
b00000000000000000000000000000010 #
b00000000000000000000000000000011 $
b00000000000000000000000000000001 %
b0001 '
1(
#5
0(
#6
b00000000000000000000000000000011 #
b00000000000000000000000000000100 $
1(
b0001 *
b00000000000000000000000000000001 +
#7
0(
#8
b00000000000000000000000000000100 #
b00000000000000000000000000000101 $
b00000000000000000000000000000010 %
b0010 '
1(
#9
0(
#10
b00000000000000000000000000000101 #
b00000000000000000000000000000110 $
1(
b0010 *
b00000000000000000000000000000010 +
#11
0(
#12
b00000000000000000000000000000110 #
b00000000000000000000000000000111 $
b00000000000000000000000000000011 %
b0011 '
1(
#13
0(
#14
b00000000000000000000000000000111 #
b00000000000000000000000000001000 $
1(
b0011 *
b00000000000000000000000000000011 +
#15
0(
#16
b00000000000000000000000000001000 #
b00000000000000000000000000001001 $
b00000000000000000000000000000100 %
b0100 '
1(
#17
0(
#18
b00000000000000000000000000001001 #
b00000000000000000000000000001010 $
1(
b0100 *
b00000000000000000000000000000100 +
#19
0(
#20
b00000000000000000000000000001010 #
b00000000000000000000000000001011 $
b00000000000000000000000000000101 %
b0101 '
1(
#21
0(
#22
b00000000000000000000000000001011 #
b00000000000000000000000000001100 $
1(
b0101 *
b00000000000000000000000000000101 +
#23
0(
#24
b00000000000000000000000000001100 #
b00000000000000000000000000001101 $
b00000000000000000000000000000110 %
b0110 '
1(
#25
0(
#26
b00000000000000000000000000001101 #
b00000000000000000000000000001110 $
1(
b0110 *
b00000000000000000000000000000110 +
#27
0(
#28
b00000000000000000000000000001110 #
b00000000000000000000000000001111 $
b00000000000000000000000000000111 %
b0111 '
1(
#29
0(
#30
b00000000000000000000000000001111 #
b00000000000000000000000000010000 $
1(
b0111 *
b00000000000000000000000000000111 +
#31
0(
#32
b00000000000000000000000000010000 #
b00000000000000000000000000010001 $
b00000000000000000000000000001000 %
b1000 '
1(
#33
0(
#34
b00000000000000000000000000010001 #
b00000000000000000000000000010010 $
1(
b1000 *
b00000000000000000000000000001000 +
#35
0(
#36
b00000000000000000000000000010010 #
b00000000000000000000000000010011 $
b00000000000000000000000000001001 %
b1001 '
1(
#37
0(
#38
b00000000000000000000000000010011 #
b00000000000000000000000000010100 $
1(
b1001 *
b00000000000000000000000000001001 +
#39
0(
#40
b00000000000000000000000000010100 #
b00000000000000000000000000010101 $
b00000000000000000000000000001010 %
b1010 '
1(
#41
0(
#42
b00000000000000000000000000010101 #
b00000000000000000000000000010110 $
1(
b1010 *
b00000000000000000000000000001010 +
#43
0(
#44
b00000000000000000000000000010110 #
b00000000000000000000000000010111 $
b00000000000000000000000000001011 %
b1011 '
1(
#45
0(
#46
b00000000000000000000000000010111 #
b00000000000000000000000000011000 $
1(
b1011 *
b00000000000000000000000000001011 +
#47
0(
#48
b00000000000000000000000000011000 #
b00000000000000000000000000011001 $
b00000000000000000000000000001100 %
b1100 '
1(
#49
0(
#50
b00000000000000000000000000011001 #
b00000000000000000000000000011010 $
1(
b1100 *
b00000000000000000000000000001100 +
#51
0(
#52
b00000000000000000000000000011010 #
b00000000000000000000000000011011 $
b00000000000000000000000000001101 %
b1101 '
1(
#53
0(
#54
b00000000000000000000000000011011 #
b00000000000000000000000000011100 $
1(
b1101 *
b00000000000000000000000000001101 +
#55
0(
#56
b00000000000000000000000000011100 #
b00000000000000000000000000011101 $
b00000000000000000000000000001110 %
b1110 '
1(
#57
0(
#58
b00000000000000000000000000011101 #
b00000000000000000000000000011110 $
1(
b1110 *
b00000000000000000000000000001110 +
#59
0(
#60
b00000000000000000000000000011110 #
b00000000000000000000000000011111 $
b00000000000000000000000000001111 %
b1111 '
1(
#61
0(
#62
b00000000000000000000000000011111 #
b00000000000000000000000000100000 $
1(
b1111 *
b00000000000000000000000000001111 +
#63
0(
#64
b00000000000000000000000000100000 #
b00000000000000000000000000100001 $
b00000000000000000000000000000000 %
b0000 '
1(
#65
0(
#66
b00000000000000000000000000100001 #
b00000000000000000000000000100010 $
1(
b0000 *
b00000000000000000000000000000000 +
#67
0(
#68
b00000000000000000000000000100010 #
b00000000000000000000000000100011 $
b00000000000000000000000000000001 %
b0001 '
1(
#69
0(
#70
b00000000000000000000000000100011 #
b00000000000000000000000000100100 $
1(
b0001 *
b00000000000000000000000000000001 +
#71
0(
#72
b00000000000000000000000000100100 #
b00000000000000000000000000100101 $
b00000000000000000000000000000010 %
b0010 '
1(
#73
0(
#74
b00000000000000000000000000100101 #
b00000000000000000000000000100110 $
1(
b0010 *
b00000000000000000000000000000010 +
#75
0(
#76
b00000000000000000000000000100110 #
b00000000000000000000000000100111 $
b00000000000000000000000000000011 %
b0011 '
1(
#77
0(
#78
b00000000000000000000000000100111 #
b00000000000000000000000000101000 $
1(
b0011 *
b00000000000000000000000000000011 +
#79
0(
#80
b00000000000000000000000000101000 #
b00000000000000000000000000101001 $
b00000000000000000000000000000100 %
b0100 '
1(
#81
0(
#82
b00000000000000000000000000101001 #
b00000000000000000000000000101010 $
1(
b0100 *
b00000000000000000000000000000100 +
#83
0(
#84
b00000000000000000000000000101010 #
b00000000000000000000000000101011 $
b00000000000000000000000000000101 %
b0101 '
1(
#85
0(
#86
b00000000000000000000000000101011 #
b00000000000000000000000000101100 $
1(
b0101 *
b00000000000000000000000000000101 +
#87
0(
#88
b00000000000000000000000000101100 #
b00000000000000000000000000101101 $
b00000000000000000000000000000110 %
b0110 '
1(
#89
0(
#90
b00000000000000000000000000101101 #
b00000000000000000000000000101110 $
1(
b0110 *
b00000000000000000000000000000110 +
#91
0(
#92
b00000000000000000000000000101110 #
b00000000000000000000000000101111 $
b00000000000000000000000000000111 %
b0111 '
1(
#93
0(
#94
b00000000000000000000000000101111 #
b00000000000000000000000000110000 $
1(
b0111 *
b00000000000000000000000000000111 +
#95
0(
#96
b00000000000000000000000000110000 #
b00000000000000000000000000110001 $
b00000000000000000000000000001000 %
b1000 '
1(
#97
0(
#98
b00000000000000000000000000110001 #
b00000000000000000000000000110010 $
1(
b1000 *
b00000000000000000000000000001000 +
#99
0(
#100
b00000000000000000000000000110010 #
b00000000000000000000000000110011 $
b00000000000000000000000000001001 %
b1001 '
1(
#101
0(
#102
b00000000000000000000000000110011 #
b00000000000000000000000000110100 $
1(
b1001 *
b00000000000000000000000000001001 +
#103
0(
#104
b00000000000000000000000000110100 #
b00000000000000000000000000110101 $
b00000000000000000000000000001010 %
b1010 '
1(
#105
0(
#106
b00000000000000000000000000110101 #
b00000000000000000000000000110110 $
1(
b1010 *
b00000000000000000000000000001010 +
#107
0(
#108
b00000000000000000000000000110110 #
b00000000000000000000000000110111 $
b00000000000000000000000000001011 %
b1011 '
1(
#109
0(
#110
b00000000000000000000000000110111 #
b00000000000000000000000000111000 $
1(
b1011 *
b00000000000000000000000000001011 +
#111
0(
#112
b00000000000000000000000000111000 #
b00000000000000000000000000111001 $
b00000000000000000000000000001100 %
b1100 '
1(
#113
0(
#114
b00000000000000000000000000111001 #
b00000000000000000000000000111010 $
1(
b1100 *
b00000000000000000000000000001100 +
#115
0(
#116
b00000000000000000000000000111010 #
b00000000000000000000000000111011 $
b00000000000000000000000000001101 %
b1101 '
1(
#117
0(
#118
b00000000000000000000000000111011 #
b00000000000000000000000000111100 $
1(
b1101 *
b00000000000000000000000000001101 +
#119
0(
#120
b00000000000000000000000000111100 #
b00000000000000000000000000111101 $
b00000000000000000000000000001110 %
b1110 '
1(
#121
0(
#122
b00000000000000000000000000111101 #
b00000000000000000000000000111110 $
1(
b1110 *
b00000000000000000000000000001110 +
#123
0(
#124
b00000000000000000000000000111110 #
b00000000000000000000000000111111 $
b00000000000000000000000000001111 %
b1111 '
1(
#125
0(
#126
b00000000000000000000000000111111 #
b00000000000000000000000001000000 $
1(
b1111 *
b00000000000000000000000000001111 +
#127
0(
#128
b00000000000000000000000001000000 #
b00000000000000000000000001000001 $
b00000000000000000000000000000000 %
b0000 '
1(
#129
0(
#130
b00000000000000000000000001000001 #
b00000000000000000000000001000010 $
1(
b0000 *
b00000000000000000000000000000000 +
#131
0(
#132
b00000000000000000000000001000010 #
b00000000000000000000000001000011 $
b00000000000000000000000000000001 %
b0001 '
1(
#133
0(
#134
b00000000000000000000000001000011 #
b00000000000000000000000001000100 $
1(
b0001 *
b00000000000000000000000000000001 +
#135
0(
#136
b00000000000000000000000001000100 #
b00000000000000000000000001000101 $
b00000000000000000000000000000010 %
b0010 '
1(
#137
0(
#138
b00000000000000000000000001000101 #
b00000000000000000000000001000110 $
1(
b0010 *
b00000000000000000000000000000010 +
#139
0(
#140
b00000000000000000000000001000110 #
b00000000000000000000000001000111 $
b00000000000000000000000000000011 %
b0011 '
1(
#141
0(
#142
b00000000000000000000000001000111 #
b00000000000000000000000001001000 $
1(
b0011 *
b00000000000000000000000000000011 +
#143
0(
#144
b00000000000000000000000001001000 #
b00000000000000000000000001001001 $
b00000000000000000000000000000100 %
b0100 '
1(
#145
0(
#146
b00000000000000000000000001001001 #
b00000000000000000000000001001010 $
1(
b0100 *
b00000000000000000000000000000100 +
#147
0(
#148
b00000000000000000000000001001010 #
b00000000000000000000000001001011 $
b00000000000000000000000000000101 %
b0101 '
1(
#149
0(
#150
b00000000000000000000000001001011 #
b00000000000000000000000001001100 $
1(
b0101 *
b00000000000000000000000000000101 +
#151
0(
#152
b00000000000000000000000001001100 #
b00000000000000000000000001001101 $
b00000000000000000000000000000110 %
b0110 '
1(
#153
0(
#154
b00000000000000000000000001001101 #
b00000000000000000000000001001110 $
1(
b0110 *
b00000000000000000000000000000110 +
#155
0(
#156
b00000000000000000000000001001110 #
b00000000000000000000000001001111 $
b00000000000000000000000000000111 %
b0111 '
1(
#157
0(
#158
b00000000000000000000000001001111 #
b00000000000000000000000001010000 $
1(
b0111 *
b00000000000000000000000000000111 +
#159
0(
#160
b00000000000000000000000001010000 #
b00000000000000000000000001010001 $
b00000000000000000000000000001000 %
b1000 '
1(
#161
0(
#162
b00000000000000000000000001010001 #
b00000000000000000000000001010010 $
1(
b1000 *
b00000000000000000000000000001000 +
#163
0(
#164
b00000000000000000000000001010010 #
b00000000000000000000000001010011 $
b00000000000000000000000000001001 %
b1001 '
1(
#165
0(
#166
b00000000000000000000000001010011 #
b00000000000000000000000001010100 $
1(
b1001 *
b00000000000000000000000000001001 +
#167
0(
#168
b00000000000000000000000001010100 #
b00000000000000000000000001010101 $
b00000000000000000000000000001010 %
b1010 '
1(
#169
0(
#170
b00000000000000000000000001010101 #
b00000000000000000000000001010110 $
1(
b1010 *
b00000000000000000000000000001010 +
#171
0(
#172
b00000000000000000000000001010110 #
b00000000000000000000000001010111 $
b00000000000000000000000000001011 %
b1011 '
1(
#173
0(
#174
b00000000000000000000000001010111 #
b00000000000000000000000001011000 $
1(
b1011 *
b00000000000000000000000000001011 +
#175
0(
#176
b00000000000000000000000001011000 #
b00000000000000000000000001011001 $
b00000000000000000000000000001100 %
b1100 '
1(
#177
0(
#178
b00000000000000000000000001011001 #
b00000000000000000000000001011010 $
1(
b1100 *
b00000000000000000000000000001100 +
#179
0(
#180
b00000000000000000000000001011010 #
b00000000000000000000000001011011 $
b00000000000000000000000000001101 %
b1101 '
1(
#181
0(
#182
b00000000000000000000000001011011 #
b00000000000000000000000001011100 $
1(
b1101 *
b00000000000000000000000000001101 +
#183
0(
#184
b00000000000000000000000001011100 #
b00000000000000000000000001011101 $
b00000000000000000000000000001110 %
b1110 '
1(
#185
0(
#186
b00000000000000000000000001011101 #
b00000000000000000000000001011110 $
1(
b1110 *
b00000000000000000000000000001110 +
#187
0(
#188
b00000000000000000000000001011110 #
b00000000000000000000000001011111 $
b00000000000000000000000000001111 %
b1111 '
1(
#189
0(
#190
b00000000000000000000000001011111 #
b00000000000000000000000001100000 $
1(
b1111 *
b00000000000000000000000000001111 +
#191
0(
#192
b00000000000000000000000001100000 #
b00000000000000000000000001100001 $
b00000000000000000000000000000000 %
b0000 '
1(
#193
0(
#194
b00000000000000000000000001100001 #
b00000000000000000000000001100010 $
1(
b0000 *
b00000000000000000000000000000000 +
#195
0(
#196
b00000000000000000000000001100010 #
b00000000000000000000000001100011 $
b00000000000000000000000000000001 %
b0001 '
1(
#197
0(
#198
b00000000000000000000000001100011 #
b00000000000000000000000001100100 $
1(
b0001 *
b00000000000000000000000000000001 +
#199
0(
#200
b00000000000000000000000001100100 #
b00000000000000000000000001100101 $
b00000000000000000000000000000010 %
b0010 '
1(
#201
0(
#202
b00000000000000000000000001100101 #
b00000000000000000000000001100110 $
1(
b0010 *
b00000000000000000000000000000010 +
#203
0(
#204
b00000000000000000000000001100110 #
b00000000000000000000000001100111 $
b00000000000000000000000000000011 %
b0011 '
1(
#205
0(
#206
b00000000000000000000000001100111 #
b00000000000000000000000001101000 $
1(
b0011 *
b00000000000000000000000000000011 +
#207
0(
#208
b00000000000000000000000001101000 #
b00000000000000000000000001101001 $
b00000000000000000000000000000100 %
b0100 '
1(
#209
0(
#210
b00000000000000000000000001101001 #
b00000000000000000000000001101010 $
1(
b0100 *
b00000000000000000000000000000100 +
#211
0(
#212
b00000000000000000000000001101010 #
b00000000000000000000000001101011 $
b00000000000000000000000000000101 %
b0101 '
1(
#213
0(
#214
b00000000000000000000000001101011 #
b00000000000000000000000001101100 $
1(
b0101 *
b00000000000000000000000000000101 +
#215
0(
#216
b00000000000000000000000001101100 #
b00000000000000000000000001101101 $
b00000000000000000000000000000110 %
b0110 '
1(
#217
0(
#218
b00000000000000000000000001101101 #
b00000000000000000000000001101110 $
1(
b0110 *
b00000000000000000000000000000110 +
#219
0(
#220
b00000000000000000000000001101110 #
b00000000000000000000000001101111 $
b00000000000000000000000000000111 %
b0111 '
1(
#221
0(
#222
b00000000000000000000000001101111 #
b00000000000000000000000001110000 $
1(
b0111 *
b00000000000000000000000000000111 +
#223
0(
#224
b00000000000000000000000001110000 #
b00000000000000000000000001110001 $
b00000000000000000000000000001000 %
b1000 '
1(
#225
0(
#226
b00000000000000000000000001110001 #
b00000000000000000000000001110010 $
1(
b1000 *
b00000000000000000000000000001000 +
#227
0(
#228
b00000000000000000000000001110010 #
b00000000000000000000000001110011 $
b00000000000000000000000000001001 %
b1001 '
1(
#229
0(
#230
b00000000000000000000000001110011 #
b00000000000000000000000001110100 $
1(
b1001 *
b00000000000000000000000000001001 +
#231
0(
#232
b00000000000000000000000001110100 #
b00000000000000000000000001110101 $
b00000000000000000000000000001010 %
b1010 '
1(
#233
0(
#234
b00000000000000000000000001110101 #
b00000000000000000000000001110110 $
1(
b1010 *
b00000000000000000000000000001010 +
#235
0(
#236
b00000000000000000000000001110110 #
b00000000000000000000000001110111 $
b00000000000000000000000000001011 %
b1011 '
1(
#237
0(
#238
b00000000000000000000000001110111 #
b00000000000000000000000001111000 $
1(
b1011 *
b00000000000000000000000000001011 +
#239
0(
#240
b00000000000000000000000001111000 #
b00000000000000000000000001111001 $
b00000000000000000000000000001100 %
b1100 '
1(
#241
0(
#242
b00000000000000000000000001111001 #
b00000000000000000000000001111010 $
1(
b1100 *
b00000000000000000000000000001100 +
#243
0(
#244
b00000000000000000000000001111010 #
b00000000000000000000000001111011 $
b00000000000000000000000000001101 %
b1101 '
1(
#245
0(
#246
b00000000000000000000000001111011 #
b00000000000000000000000001111100 $
1(
b1101 *
b00000000000000000000000000001101 +
#247
0(
#248
b00000000000000000000000001111100 #
b00000000000000000000000001111101 $
b00000000000000000000000000001110 %
b1110 '
1(
#249
0(
#250
b00000000000000000000000001111101 #
b00000000000000000000000001111110 $
1(
b1110 *
b00000000000000000000000000001110 +
#251
0(
#252
b00000000000000000000000001111110 #
b00000000000000000000000001111111 $
b00000000000000000000000000001111 %
b1111 '
1(
#253
0(
#254
b00000000000000000000000001111111 #
b00000000000000000000000010000000 $
1(
b1111 *
b00000000000000000000000000001111 +
#255
0(
#256
b00000000000000000000000010000000 #
b00000000000000000000000010000001 $
b00000000000000000000000000000000 %
b0000 '
1(
#257
0(
#258
b00000000000000000000000010000001 #
b00000000000000000000000010000010 $
1(
b0000 *
b00000000000000000000000000000000 +
#259
0(
#260
b00000000000000000000000010000010 #
b00000000000000000000000010000011 $
b00000000000000000000000000000001 %
b0001 '
1(
#261
0(
#262
b00000000000000000000000010000011 #
b00000000000000000000000010000100 $
1(
b0001 *
b00000000000000000000000000000001 +
#263
0(
#264
b00000000000000000000000010000100 #
b00000000000000000000000010000101 $
b00000000000000000000000000000010 %
b0010 '
1(
#265
0(
#266
b00000000000000000000000010000101 #
b00000000000000000000000010000110 $
1(
b0010 *
b00000000000000000000000000000010 +
#267
0(
#268
b00000000000000000000000010000110 #
b00000000000000000000000010000111 $
b00000000000000000000000000000011 %
b0011 '
1(
#269
0(
#270
b00000000000000000000000010000111 #
b00000000000000000000000010001000 $
1(
b0011 *
b00000000000000000000000000000011 +
#271
0(
#272
b00000000000000000000000010001000 #
b00000000000000000000000010001001 $
b00000000000000000000000000000100 %
b0100 '
1(
#273
0(
#274
b00000000000000000000000010001001 #
b00000000000000000000000010001010 $
1(
b0100 *
b00000000000000000000000000000100 +
#275
0(
#276
b00000000000000000000000010001010 #
b00000000000000000000000010001011 $
b00000000000000000000000000000101 %
b0101 '
1(
#277
0(
#278
b00000000000000000000000010001011 #
b00000000000000000000000010001100 $
1(
b0101 *
b00000000000000000000000000000101 +
#279
0(
#280
b00000000000000000000000010001100 #
b00000000000000000000000010001101 $
b00000000000000000000000000000110 %
b0110 '
1(
#281
0(
#282
b00000000000000000000000010001101 #
b00000000000000000000000010001110 $
1(
b0110 *
b00000000000000000000000000000110 +
#283
0(
#284
b00000000000000000000000010001110 #
b00000000000000000000000010001111 $
b00000000000000000000000000000111 %
b0111 '
1(
#285
0(
#286
b00000000000000000000000010001111 #
b00000000000000000000000010010000 $
1(
b0111 *
b00000000000000000000000000000111 +
#287
0(
#288
b00000000000000000000000010010000 #
b00000000000000000000000010010001 $
b00000000000000000000000000001000 %
b1000 '
1(
#289
0(
#290
b00000000000000000000000010010001 #
b00000000000000000000000010010010 $
1(
b1000 *
b00000000000000000000000000001000 +
#291
0(
#292
b00000000000000000000000010010010 #
b00000000000000000000000010010011 $
b00000000000000000000000000001001 %
b1001 '
1(
#293
0(
#294
b00000000000000000000000010010011 #
b00000000000000000000000010010100 $
1(
b1001 *
b00000000000000000000000000001001 +
#295
0(
#296
b00000000000000000000000010010100 #
b00000000000000000000000010010101 $
b00000000000000000000000000001010 %
b1010 '
1(
#297
0(
#298
b00000000000000000000000010010101 #
b00000000000000000000000010010110 $
1(
b1010 *
b00000000000000000000000000001010 +
#299
0(
#300
b00000000000000000000000010010110 #
b00000000000000000000000010010111 $
b00000000000000000000000000001011 %
b1011 '
1(
#301
0(
#302
b00000000000000000000000010010111 #
b00000000000000000000000010011000 $
1(
b1011 *
b00000000000000000000000000001011 +
#303
0(
#304
b00000000000000000000000010011000 #
b00000000000000000000000010011001 $
b00000000000000000000000000001100 %
b1100 '
1(
#305
0(
#306
b00000000000000000000000010011001 #
b00000000000000000000000010011010 $
1(
b1100 *
b00000000000000000000000000001100 +
#307
0(
#308
b00000000000000000000000010011010 #
b00000000000000000000000010011011 $
b00000000000000000000000000001101 %
b1101 '
1(
#309
0(
#310
b00000000000000000000000010011011 #
b00000000000000000000000010011100 $
1(
b1101 *
b00000000000000000000000000001101 +
#311
0(
#312
b00000000000000000000000010011100 #
b00000000000000000000000010011101 $
b00000000000000000000000000001110 %
b1110 '
1(
#313
0(
#314
b00000000000000000000000010011101 #
b00000000000000000000000010011110 $
1(
b1110 *
b00000000000000000000000000001110 +
#315
0(
#316
b00000000000000000000000010011110 #
b00000000000000000000000010011111 $
b00000000000000000000000000001111 %
b1111 '
1(
#317
0(
#318
b00000000000000000000000010011111 #
b00000000000000000000000010100000 $
1(
b1111 *
b00000000000000000000000000001111 +
#319
0(
#320
b00000000000000000000000010100000 #
b00000000000000000000000010100001 $
b00000000000000000000000000000000 %
b0000 '
1(
#321
0(
#322
b00000000000000000000000010100001 #
b00000000000000000000000010100010 $
1(
b0000 *
b00000000000000000000000000000000 +
#323
0(
#324
b00000000000000000000000010100010 #
b00000000000000000000000010100011 $
b00000000000000000000000000000001 %
b0001 '
1(
#325
0(
#326
b00000000000000000000000010100011 #
b00000000000000000000000010100100 $
1(
b0001 *
b00000000000000000000000000000001 +
#327
0(
#328
b00000000000000000000000010100100 #
b00000000000000000000000010100101 $
b00000000000000000000000000000010 %
b0010 '
1(
#329
0(
#330
b00000000000000000000000010100101 #
b00000000000000000000000010100110 $
1(
b0010 *
b00000000000000000000000000000010 +
#331
0(
#332
b00000000000000000000000010100110 #
b00000000000000000000000010100111 $
b00000000000000000000000000000011 %
b0011 '
1(
#333
0(
#334
b00000000000000000000000010100111 #
b00000000000000000000000010101000 $
1(
b0011 *
b00000000000000000000000000000011 +
#335
0(
#336
b00000000000000000000000010101000 #
b00000000000000000000000010101001 $
b00000000000000000000000000000100 %
b0100 '
1(
#337
0(
#338
b00000000000000000000000010101001 #
b00000000000000000000000010101010 $
1(
b0100 *
b00000000000000000000000000000100 +
#339
0(
#340
b00000000000000000000000010101010 #
b00000000000000000000000010101011 $
b00000000000000000000000000000101 %
b0101 '
1(
#341
0(
#342
b00000000000000000000000010101011 #
b00000000000000000000000010101100 $
1(
b0101 *
b00000000000000000000000000000101 +
#343
0(
#344
b00000000000000000000000010101100 #
b00000000000000000000000010101101 $
b00000000000000000000000000000110 %
b0110 '
1(
#345
0(
#346
b00000000000000000000000010101101 #
b00000000000000000000000010101110 $
1(
b0110 *
b00000000000000000000000000000110 +
#347
0(
#348
b00000000000000000000000010101110 #
b00000000000000000000000010101111 $
b00000000000000000000000000000111 %
b0111 '
1(
#349
0(
#350
b00000000000000000000000010101111 #
b00000000000000000000000010110000 $
1(
b0111 *
b00000000000000000000000000000111 +
#351
0(
#352
b00000000000000000000000010110000 #
b00000000000000000000000010110001 $
b00000000000000000000000000001000 %
b1000 '
1(
#353
0(
#354
b00000000000000000000000010110001 #
b00000000000000000000000010110010 $
1(
b1000 *
b00000000000000000000000000001000 +
#355
0(
#356
b00000000000000000000000010110010 #
b00000000000000000000000010110011 $
b00000000000000000000000000001001 %
b1001 '
1(
#357
0(
#358
b00000000000000000000000010110011 #
b00000000000000000000000010110100 $
1(
b1001 *
b00000000000000000000000000001001 +
#359
0(
#360
b00000000000000000000000010110100 #
b00000000000000000000000010110101 $
b00000000000000000000000000001010 %
b1010 '
1(
#361
0(
#362
b00000000000000000000000010110101 #
b00000000000000000000000010110110 $
1(
b1010 *
b00000000000000000000000000001010 +
#363
0(
#364
b00000000000000000000000010110110 #
b00000000000000000000000010110111 $
b00000000000000000000000000001011 %
b1011 '
1(
#365
0(
#366
b00000000000000000000000010110111 #
b00000000000000000000000010111000 $
1(
b1011 *
b00000000000000000000000000001011 +
#367
0(
#368
b00000000000000000000000010111000 #
b00000000000000000000000010111001 $
b00000000000000000000000000001100 %
b1100 '
1(
#369
0(
#370
b00000000000000000000000010111001 #
b00000000000000000000000010111010 $
1(
b1100 *
b00000000000000000000000000001100 +
#371
0(
#372
b00000000000000000000000010111010 #
b00000000000000000000000010111011 $
b00000000000000000000000000001101 %
b1101 '
1(
#373
0(
#374
b00000000000000000000000010111011 #
b00000000000000000000000010111100 $
1(
b1101 *
b00000000000000000000000000001101 +
#375
0(
#376
b00000000000000000000000010111100 #
b00000000000000000000000010111101 $
b00000000000000000000000000001110 %
b1110 '
1(
#377
0(
#378
b00000000000000000000000010111101 #
b00000000000000000000000010111110 $
1(
b1110 *
b00000000000000000000000000001110 +
#379
0(
#380
b00000000000000000000000010111110 #
b00000000000000000000000010111111 $
b00000000000000000000000000001111 %
b1111 '
1(
#381
0(
#382
b00000000000000000000000010111111 #
b00000000000000000000000011000000 $
1(
b1111 *
b00000000000000000000000000001111 +
#383
0(
#384
b00000000000000000000000011000000 #
b00000000000000000000000011000001 $
b00000000000000000000000000000000 %
b0000 '
1(
#385
0(
#386
b00000000000000000000000011000001 #
b00000000000000000000000011000010 $
1(
b0000 *
b00000000000000000000000000000000 +
#387
0(
#388
b00000000000000000000000011000010 #
b00000000000000000000000011000011 $
b00000000000000000000000000000001 %
b0001 '
1(
#389
0(
#390
b00000000000000000000000011000011 #
b00000000000000000000000011000100 $
1(
b0001 *
b00000000000000000000000000000001 +
#391
0(
#392
b00000000000000000000000011000100 #
b00000000000000000000000011000101 $
b00000000000000000000000000000010 %
b0010 '
1(
#393
0(
#394
b00000000000000000000000011000101 #
b00000000000000000000000011000110 $
1(
b0010 *
b00000000000000000000000000000010 +
#395
0(
#396
b00000000000000000000000011000110 #
b00000000000000000000000011000111 $
b00000000000000000000000000000011 %
b0011 '
1(
#397
0(
#398
b00000000000000000000000011000111 #
b00000000000000000000000011001000 $
1(
b0011 *
b00000000000000000000000000000011 +
#399
0(
#400
b00000000000000000000000011001000 #
b00000000000000000000000011001001 $
b00000000000000000000000000000100 %
b0100 '
1(
#401
0(
#402
b00000000000000000000000011001001 #
b00000000000000000000000011001010 $
1(
b0100 *
b00000000000000000000000000000100 +
#403
0(
#404
b00000000000000000000000011001010 #
b00000000000000000000000011001011 $
b00000000000000000000000000000101 %
b0101 '
1(
#405
0(
#406
b00000000000000000000000011001011 #
b00000000000000000000000011001100 $
1(
b0101 *
b00000000000000000000000000000101 +
#407
0(
#408
b00000000000000000000000011001100 #
b00000000000000000000000011001101 $
b00000000000000000000000000000110 %
b0110 '
1(
#409
0(
#410
b00000000000000000000000011001101 #
b00000000000000000000000011001110 $
1(
b0110 *
b00000000000000000000000000000110 +
#411
0(
#412
b00000000000000000000000011001110 #
b00000000000000000000000011001111 $
b00000000000000000000000000000111 %
b0111 '
1(
#413
0(
#414
b00000000000000000000000011001111 #
b00000000000000000000000011010000 $
1(
b0111 *
b00000000000000000000000000000111 +
#415
0(
#416
b00000000000000000000000011010000 #
b00000000000000000000000011010001 $
b00000000000000000000000000001000 %
b1000 '
1(
#417
0(
#418
b00000000000000000000000011010001 #
b00000000000000000000000011010010 $
1(
b1000 *
b00000000000000000000000000001000 +
#419
0(
#420
b00000000000000000000000011010010 #
b00000000000000000000000011010011 $
b00000000000000000000000000001001 %
b1001 '
1(
#421
0(
#422
b00000000000000000000000011010011 #
b00000000000000000000000011010100 $
1(
b1001 *
b00000000000000000000000000001001 +
#423
0(
#424
b00000000000000000000000011010100 #
b00000000000000000000000011010101 $
b00000000000000000000000000001010 %
b1010 '
1(
#425
0(
#426
b00000000000000000000000011010101 #
b00000000000000000000000011010110 $
1(
b1010 *
b00000000000000000000000000001010 +
#427
0(
#428
b00000000000000000000000011010110 #
b00000000000000000000000011010111 $
b00000000000000000000000000001011 %
b1011 '
1(
#429
0(
#430
b00000000000000000000000011010111 #
b00000000000000000000000011011000 $
1(
b1011 *
b00000000000000000000000000001011 +
#431
0(
#432
b00000000000000000000000011011000 #
b00000000000000000000000011011001 $
b00000000000000000000000000001100 %
b1100 '
1(
#433
0(
#434
b00000000000000000000000011011001 #
b00000000000000000000000011011010 $
1(
b1100 *
b00000000000000000000000000001100 +
#435
0(
