rtl/rom.sv
`default_nettype none

/* verilator lint_off UNUSED */

module rom
#(
  parameter Contents = "",
  parameter Depth = 0,

  localparam DataWidth = 32,
  localparam AddrWidth = $clog2(Depth),
  localparam SelWidth = DataWidth / 8
)
(
  input wire logic clk,

  output logic [DataWidth-1:0] bus_data_s,
  output logic bus_ack,
  output logic bus_stall,
  output logic bus_err,

  input wire logic [DataWidth-1:0] bus_data_m,
  input wire logic [AddrWidth-1:0] bus_addr,
  input wire logic [SelWidth-1:0] bus_sel,
  input wire logic bus_cyc,
  input wire logic bus_stb,
  input wire logic bus_we
);

logic [DataWidth-1:0] mem [0:Depth-1];

initial begin
  bus_ack = '0;

  $readmemh(Contents, mem);
end

assign bus_err = '0;
assign bus_stall = '0;

always_ff @(posedge clk) begin
  bus_data_s <= mem[bus_addr];
  bus_ack <= bus_stb;
end

endmodule

rtl/led_interface.sv
`default_nettype none

module led_interface
#(
  localparam DataWidth = 32,
  localparam AddrWidth = 32,
  localparam SelWidth = DataWidth / 8
)
(
  input wire logic clk,
  input wire logic reset_n,

  output logic [DataWidth-1:0] bus_data_s,
  output logic bus_ack,
  output logic bus_stall,
  output logic bus_err,

  input wire logic [DataWidth-1:0] bus_data_m,
  input wire logic [AddrWidth-1:0] bus_addr,
  input wire logic [SelWidth-1:0] bus_sel,
  input wire logic bus_cyc,
  input wire logic bus_stb,
  input wire logic bus_we,

  output logic [3:0] leds
);

logic [3:0] leds_next;

initial begin
  leds = '0;
  bus_ack = '0;
end

always_comb begin
  bus_data_s = {28'h0, leds};
  bus_stall = '0;
  bus_err = '0;

  leds_next = leds;

  if (bus_stb && bus_we && bus_sel[0]) begin
    leds_next = bus_data_m[3:0];
  end
end

always_ff @(posedge clk) begin
  if(!reset_n) begin
    leds <= '0;
    bus_ack <= '0;
  end else begin
    leds <= leds_next;
    bus_ack <= bus_stb;
  end
end

endmodule

rtl/bus_decoder.sv
`default_nettype none

module bus_decoder
#(
  parameter MaskWidth = 0,
  parameter TagWidth = 0,
  parameter AddrWidth = 32,

  localparam DataWidth = AddrWidth - MaskWidth
)
(
  input wire logic [AddrWidth-1:0] addr,
  output logic [AddrWidth-1:0] addr_masked,
  output logic [TagWidth-1:0] tag
);

assign tag = addr[DataWidth + TagWidth - 1:DataWidth];
assign addr_masked = { {MaskWidth{1'b0}}, addr[DataWidth-1:0] };

endmodule

rtl/wb_multiplexer.sv
`default_nettype none

module wb_multiplexer
#(
  parameter Count = 0,
  parameter MaskWidth = 0,

  parameter DataWidth = 32,
  parameter AddrWidth = 32,

  localparam SelWidth = DataWidth / 8,
  localparam TagWidth = $clog2(Count)
)
(
  input wire logic clk,
  input wire logic reset_n,

  // Master
  output logic [DataWidth-1:0] m_data_s,
  output logic m_ack,
  output logic m_stall,
  output logic m_err,

  input wire logic [DataWidth-1:0] m_data_m,
  input wire logic [AddrWidth-1:0] m_addr,
  input wire logic [SelWidth-1:0] m_sel,
  input wire logic m_cyc,
  input wire logic m_stb,
  input wire logic m_we,

  // Slaves
  input logic [DataWidth-1:0] s_data_s [Count],
  input logic s_ack [Count],
  input logic s_stall [Count],
  input logic s_err [Count],

  output wire logic [DataWidth-1:0] s_data_m [Count],
  output wire logic [AddrWidth-1:0] s_addr [Count],
  output wire logic [SelWidth-1:0] s_sel [Count],
  output wire logic s_cyc [Count],
  output wire logic s_stb [Count],
  output wire logic s_we [Count]
);

logic [AddrWidth-1:0] addr_masked;
logic [TagWidth-1:0] tag;

logic [AddrWidth-1:0] addr;
logic [AddrWidth-1:0] addr_reg;

always_comb begin
  addr = m_stb ? m_addr : addr_reg;
end

always_ff @(posedge clk) begin
  addr_reg <= addr;
end

bus_decoder
#(
  .MaskWidth(MaskWidth),
  .TagWidth(TagWidth),
  .AddrWidth(AddrWidth)
) decoder0
(
  .addr(addr),
  .addr_masked,
  .tag
);

always_comb begin
  m_data_s = s_data_s[tag];
  m_ack = s_ack[tag];
  m_stall = s_stall[tag];
  m_err = s_err[tag];
end

for(genvar i = 0; i < Count; i += 1) begin
  assign s_we[i] = m_we;
  assign s_addr[i] = addr_masked;
  assign s_data_m[i] = m_data_m;
  assign s_sel[i] = m_sel;
  assign s_cyc[i] = tag == i ? m_cyc : '0;
  assign s_stb[i] = tag == i ? m_stb : '0;
  assign s_we[i] = m_we;
end

endmodule

rtl/sim/led_interface_top.sv
`default_nettype none

module led_interface_master
#(
  localparam DataWidth = 32,
  localparam AddrWidth = 32,
  localparam SelWidth = DataWidth / 8
)
(
  input wire logic clk,
  input wire logic reset_n,

  input wire logic [DataWidth-1:0] bus_data_s,
  input wire logic bus_ack,
  input wire logic bus_stall,
  input wire logic bus_err,

  output logic [DataWidth-1:0] bus_data_m,
  output logic [AddrWidth-1:0] bus_addr,
  output logic [SelWidth-1:0] bus_sel,
  output logic bus_cyc,
  output logic bus_stb,
  output logic bus_we
);

logic [3:0] state;
logic [3:0] state_next;

logic [DataWidth-1:0] value;
logic [DataWidth-1:0] value_next;

initial begin
  state = '0;
  value = '0;
end

always_comb begin
  state_next = state;
  value_next = value;

  bus_data_m = '0;
  bus_addr = '0;
  bus_sel = '0;
  bus_cyc = '0;
  bus_stb = '0;
  bus_we = '0;

  case (state)
    4'h0: begin // Begin read
      bus_cyc = 1'b1;
      bus_stb = 1'b1;
      bus_addr = 32'h20000000;
      if(!bus_stall) begin
        state_next = 4'h1;
      end
    end
    4'h1: begin // Wait for ack
      bus_cyc = 1'b1;
      if(bus_ack) begin
        state_next = 4'h2;
        value_next = bus_data_s;
      end
    end
    4'h2: begin // Idle
      state_next = 4'h3;
    end
    4'h3: begin // Begin write
      bus_cyc = 1'b1;
      bus_stb = 1'b1;
      bus_addr = 32'h10000000;
      bus_sel = 4'h1;
      bus_data_m = value;
      bus_we = 1'b1;
      if(!bus_stall) begin
        state_next = 4'h4;
      end
    end
    4'h4: begin // Wait for ack
      bus_cyc = 1'b1;
      if(bus_ack) begin
        state_next = 4'h5;
      end
    end
    4'h5: begin // Idle
      state_next = 4'h0;
    end
    default: ;
  endcase
end

always_ff @(posedge clk) begin
  if(!reset_n) begin
    state <= '0;
    value <= '0;
  end else begin
    state <= state_next;
    value <= value_next;
  end
end

endmodule

module led_interface_top(
  input wire logic clk,
  input wire logic reset_n,

  output logic [3:0] leds
);

localparam DataWidth = 32;
localparam AddrWidth = 32;
localparam SelWidth = DataWidth / 8;

// Master
logic [DataWidth-1:0] m_data_s;
logic m_ack;
logic m_stall;
logic m_err;
logic [DataWidth-1:0] m_data_m;
logic [AddrWidth-1:0] m_addr;
logic [SelWidth-1:0] m_sel;
logic m_cyc;
logic m_stb;
logic m_we;

// Led
logic [DataWidth-1:0] led_data_s;
logic led_ack;
logic led_stall;
logic led_err;
logic [DataWidth-1:0] led_data_m;
logic [AddrWidth-1:0] led_addr;
logic [SelWidth-1:0] led_sel;
logic led_cyc;
logic led_stb;
logic led_we;

// Rom
logic [DataWidth-1:0] rom_data_s;
logic rom_ack;
logic rom_stall;
logic rom_err;
logic [DataWidth-1:0] rom_data_m;
logic [AddrWidth-1:0] rom_addr;
logic [SelWidth-1:0] rom_sel;
logic rom_cyc;
logic rom_stb;
logic rom_we;

// Dummy
logic [DataWidth-1:0] dummy_data_s;
logic dummy_ack;
logic dummy_stall;
logic dummy_err;
logic [DataWidth-1:0] dummy_data_m;
logic [AddrWidth-1:0] dummy_addr;
logic [SelWidth-1:0] dummy_sel;
logic dummy_cyc;
logic dummy_stb;
logic dummy_we;

wb_multiplexer
#(
  .Count(3),
  .MaskWidth(4)
) wbmux0
(
  .clk,
  .reset_n,

  .m_data_s(m_data_s),
  .m_ack(m_ack),
  .m_stall(m_stall),
  .m_err(m_err),
  .m_data_m(m_data_m),
  .m_addr(m_addr),
  .m_sel(m_sel),
  .m_cyc(m_cyc),
  .m_stb(m_stb),
  .m_we(m_we),

  .s_data_s({dummy_data_s, led_data_s, rom_data_s }),
  .s_ack({dummy_ack, led_ack, rom_ack}),
  .s_stall({dummy_stall, led_stall, rom_stall}),
  .s_err({dummy_err, led_err, rom_err}),
  .s_data_m({dummy_data_m, led_data_m, rom_data_m}),
  .s_addr({dummy_addr, led_addr, rom_addr}),
  .s_sel({dummy_sel, led_sel, rom_sel}),
  .s_cyc({dummy_cyc, led_cyc, rom_cyc}),
  .s_stb({dummy_stb, led_stb, rom_stb}),
  .s_we({dummy_we, led_we, rom_we})
);

led_interface led0
(
  .clk,
  .reset_n,

  .bus_data_s(led_data_s),
  .bus_ack(led_ack),
  .bus_stall(led_stall),
  .bus_err(led_err),
  .bus_data_m(led_data_m),
  .bus_addr(led_addr),
  .bus_sel(led_sel),
  .bus_cyc(led_cyc),
  .bus_stb(led_stb),
  .bus_we(led_we),

  .leds
);

rom
#(
  .Contents("led.mem"),
  .Depth(5)
) rom0
(
  .clk,

  .bus_data_s(rom_data_s),
  .bus_ack(rom_ack),
  .bus_stall(rom_stall),
  .bus_err(rom_err),
  .bus_data_m(rom_data_m),
  .bus_addr(rom_addr),
  .bus_sel(rom_sel),
  .bus_cyc(rom_cyc),
  .bus_stb(rom_stb),
  .bus_we(rom_we)
);

led_interface_master master0
(
  .clk,
  .reset_n,

  .bus_data_s(m_data_s),
  .bus_ack(m_ack),
  .bus_stall(m_stall),
  .bus_err(m_err),
  .bus_data_m(m_data_m),
  .bus_addr(m_addr),
  .bus_sel(m_sel),
  .bus_cyc(m_cyc),
  .bus_stb(m_stb),
  .bus_we(m_we)
);

endmodule

sim/led_interface/test.vcd
$version Generated by VerilatedVcd $end
$date Thu Nov  3 21:00:09 2022 $end
$timescale 1ps $end

 $scope module TOP $end
  $var wire  1 n clk $end
  $var wire  4 p leds [3:0] $end
  $var wire  1 o reset_n $end
  $scope module led_interface_top $end
   $var wire 32 r AddrWidth [31:0] $end
   $var wire 32 r DataWidth [31:0] $end
   $var wire 32 s SelWidth [31:0] $end
   $var wire  1 n clk $end
   $var wire  1 v dummy_ack $end
   $var wire 32 H dummy_addr [31:0] $end
   $var wire  1 J dummy_cyc $end
   $var wire 32 G dummy_data_m [31:0] $end
   $var wire 32 u dummy_data_s [31:0] $end
   $var wire  1 x dummy_err $end
   $var wire  4 I dummy_sel [3:0] $end
   $var wire  1 w dummy_stall $end
   $var wire  1 K dummy_stb $end
   $var wire  1 L dummy_we $end
   $var wire  1 8 led_ack $end
   $var wire 32 : led_addr [31:0] $end
   $var wire  1 < led_cyc $end
   $var wire 32 9 led_data_m [31:0] $end
   $var wire 32 q led_data_s [31:0] $end
   $var wire  1 t led_err $end
   $var wire  4 ; led_sel [3:0] $end
   $var wire  1 t led_stall $end
   $var wire  1 = led_stb $end
   $var wire  1 > led_we $end
   $var wire  4 p leds [3:0] $end
   $var wire  1 / m_ack $end
   $var wire 32 3 m_addr [31:0] $end
   $var wire  1 5 m_cyc $end
   $var wire 32 2 m_data_m [31:0] $end
   $var wire 32 . m_data_s [31:0] $end
   $var wire  1 1 m_err $end
   $var wire  4 4 m_sel [3:0] $end
   $var wire  1 0 m_stall $end
   $var wire  1 6 m_stb $end
   $var wire  1 7 m_we $end
   $var wire  1 o reset_n $end
   $var wire  1 @ rom_ack $end
   $var wire 32 B rom_addr [31:0] $end
   $var wire  1 D rom_cyc $end
   $var wire 32 A rom_data_m [31:0] $end
   $var wire 32 ? rom_data_s [31:0] $end
   $var wire  1 t rom_err $end
   $var wire  4 C rom_sel [3:0] $end
   $var wire  1 t rom_stall $end
   $var wire  1 E rom_stb $end
   $var wire  1 F rom_we $end
   $scope module led0 $end
    $var wire 32 r AddrWidth [31:0] $end
    $var wire 32 r DataWidth [31:0] $end
    $var wire 32 s SelWidth [31:0] $end
    $var wire  1 8 bus_ack $end
    $var wire 32 : bus_addr [31:0] $end
    $var wire  1 < bus_cyc $end
    $var wire 32 9 bus_data_m [31:0] $end
    $var wire 32 q bus_data_s [31:0] $end
    $var wire  1 t bus_err $end
    $var wire  4 ; bus_sel [3:0] $end
    $var wire  1 t bus_stall $end
    $var wire  1 = bus_stb $end
    $var wire  1 > bus_we $end
    $var wire  1 n clk $end
    $var wire  4 p leds [3:0] $end
    $var wire  4 M leds_next [3:0] $end
    $var wire  1 o reset_n $end
   $upscope $end
   $scope module master0 $end
    $var wire 32 r AddrWidth [31:0] $end
    $var wire 32 r DataWidth [31:0] $end
    $var wire 32 s SelWidth [31:0] $end
    $var wire  1 / bus_ack $end
    $var wire 32 3 bus_addr [31:0] $end
    $var wire  1 5 bus_cyc $end
    $var wire 32 2 bus_data_m [31:0] $end
    $var wire 32 . bus_data_s [31:0] $end
    $var wire  1 1 bus_err $end
    $var wire  4 4 bus_sel [3:0] $end
    $var wire  1 0 bus_stall $end
    $var wire  1 6 bus_stb $end
    $var wire  1 7 bus_we $end
    $var wire  1 n clk $end
    $var wire  1 o reset_n $end
    $var wire  4 N state [3:0] $end
    $var wire  4 O state_next [3:0] $end
    $var wire 32 P value [31:0] $end
    $var wire 32 Q value_next [31:0] $end
   $upscope $end
   $scope module rom0 $end
    $var wire 32 r AddrWidth [31:0] $end
    $var wire 56 y Contents [55:0] $end
    $var wire 32 r DataWidth [31:0] $end
    $var wire 32 { Depth [31:0] $end
    $var wire 32 s SelWidth [31:0] $end
    $var wire  1 @ bus_ack $end
    $var wire 32 B bus_addr [31:0] $end
    $var wire  1 D bus_cyc $end
    $var wire 32 A bus_data_m [31:0] $end
    $var wire 32 ? bus_data_s [31:0] $end
    $var wire  1 t bus_err $end
    $var wire  4 C bus_sel [3:0] $end
    $var wire  1 t bus_stall $end
    $var wire  1 E bus_stb $end
    $var wire  1 F bus_we $end
    $var wire  1 n clk $end
    $var wire 32 # mem[0] [31:0] $end
    $var wire 32 $ mem[1] [31:0] $end
    $var wire 32 % mem[2] [31:0] $end
    $var wire 32 & mem[3] [31:0] $end
    $var wire 32 ' mem[4] [31:0] $end
   $upscope $end
   $scope module wbmux0 $end
    $var wire 32 r AddrWidth [31:0] $end
    $var wire 32 | Count [31:0] $end
    $var wire 32 r DataWidth [31:0] $end
    $var wire 32 s MaskWidth [31:0] $end
    $var wire 32 s SelWidth [31:0] $end
    $var wire 32 } TagWidth [31:0] $end
    $var wire 32 l addr [31:0] $end
    $var wire 32 j addr_masked [31:0] $end
    $var wire 32 m addr_reg [31:0] $end
    $var wire  1 n clk $end
    $var wire  1 / m_ack $end
    $var wire 32 3 m_addr [31:0] $end
    $var wire  1 5 m_cyc $end
    $var wire 32 2 m_data_m [31:0] $end
    $var wire 32 . m_data_s [31:0] $end
    $var wire  1 1 m_err $end
    $var wire  4 4 m_sel [3:0] $end
    $var wire  1 0 m_stall $end
    $var wire  1 6 m_stb $end
    $var wire  1 7 m_we $end
    $var wire  1 o reset_n $end
    $var wire  1 U s_ack[0] $end
    $var wire  1 V s_ack[1] $end
    $var wire  1 W s_ack[2] $end
    $var wire 32 [ s_addr[0] [31:0] $end
    $var wire 32 \ s_addr[1] [31:0] $end
    $var wire 32 ] s_addr[2] [31:0] $end
    $var wire  1 a s_cyc[0] $end
    $var wire  1 b s_cyc[1] $end
    $var wire  1 c s_cyc[2] $end
    $var wire 32 X s_data_m[0] [31:0] $end
    $var wire 32 Y s_data_m[1] [31:0] $end
    $var wire 32 Z s_data_m[2] [31:0] $end
    $var wire 32 R s_data_s[0] [31:0] $end
    $var wire 32 S s_data_s[1] [31:0] $end
    $var wire 32 T s_data_s[2] [31:0] $end
    $var wire  1 + s_err[0] $end
    $var wire  1 , s_err[1] $end
    $var wire  1 - s_err[2] $end
    $var wire  4 ^ s_sel[0] [3:0] $end
    $var wire  4 _ s_sel[1] [3:0] $end
    $var wire  4 ` s_sel[2] [3:0] $end
    $var wire  1 ( s_stall[0] $end
    $var wire  1 ) s_stall[1] $end
    $var wire  1 * s_stall[2] $end
    $var wire  1 d s_stb[0] $end
    $var wire  1 e s_stb[1] $end
    $var wire  1 f s_stb[2] $end
    $var wire  1 g s_we[0] $end
    $var wire  1 h s_we[1] $end
    $var wire  1 i s_we[2] $end
    $var wire  2 k tag [1:0] $end
    $scope module decoder0 $end
     $var wire 32 r AddrWidth [31:0] $end
     $var wire 32 ~ DataWidth [31:0] $end
     $var wire 32 s MaskWidth [31:0] $end
     $var wire 32 } TagWidth [31:0] $end
     $var wire 32 l addr [31:0] $end
     $var wire 32 j addr_masked [31:0] $end
     $var wire  2 k tag [1:0] $end
    $upscope $end
   $upscope $end
  $upscope $end
 $upscope $end
$enddefinitions $end


#0
b11011110101011011011111011101111 #
b11111010110111101011101010111110 $
b00000000000000000000000000000000 %
b00000000000000000000000000000000 &
b00000000000000000000000000000000 '
0(
0)
0*
0+
0,
0-
b00000000000000000000000000000000 .
0/
00
01
b00000000000000000000000000000000 2
b00100000000000000000000000000000 3
b0000 4
15
16
07
08
b00000000000000000000000000000000 9
b00000000000000000000000000000000 :
b0000 ;
0<
0=
0>
b00000000000000000000000000000000 ?
0@
b00000000000000000000000000000000 A
b00000000000000000000000000000000 B
b0000 C
1D
1E
0F
b00000000000000000000000000000000 G
b00000000000000000000000000000000 H
b0000 I
0J
0K
0L
b0000 M
b0000 N
b0001 O
b00000000000000000000000000000000 P
b00000000000000000000000000000000 Q
b00000000000000000000000000000000 R
b00000000000000000000000000000000 S
b00000000000000000000000000000000 T
0U
0V
0W
b00000000000000000000000000000000 X
b00000000000000000000000000000000 Y
b00000000000000000000000000000000 Z
b00000000000000000000000000000000 [
b00000000000000000000000000000000 \
b00000000000000000000000000000000 ]
b0000 ^
b0000 _
b0000 `
0a
0b
1c
0d
0e
1f
0g
0h
0i
b00000000000000000000000000000000 j
b10 k
b00100000000000000000000000000000 l
b00000000000000000000000000000000 m
0n
0o
b0000 p
b00000000000000000000000000000000 q
b00000000000000000000000000100000 r
b00000000000000000000000000000100 s
0t
b00000000000000000000000000000000 u
0v
0w
0x
b01101100011001010110010000101110011011010110010101101101 y
b00000000000000000000000000000101 {
b00000000000000000000000000000011 |
b00000000000000000000000000000010 }
b00000000000000000000000000011100 ~
#1
1o
#2
b11011110101011011011111011101111 .
1/
b00000000000000000000000000000000 3
06
b11011110101011011011111011101111 ?
1@
0E
b0001 N
b0010 O
b11011110101011011011111011101111 Q
b11011110101011011011111011101111 T
1W
0f
b00100000000000000000000000000000 m
1n
#3
0n
#4
0/
05
0@
0D
b0010 N
b0011 O
b11011110101011011011111011101111 P
0W
0c
1n
#5
0n
#6
b00000000000000000000000000000000 .
b11011110101011011011111011101111 2
b00010000000000000000000000000000 3
b0001 4
15
16
17
b11011110101011011011111011101111 9
b0001 ;
1<
1=
1>
b11011110101011011011111011101111 A
b0001 C
1F
b11011110101011011011111011101111 G
b0001 I
1L
b1111 M
b0011 N
b0100 O
b11011110101011011011111011101111 X
b11011110101011011011111011101111 Y
b11011110101011011011111011101111 Z
b0001 ^
b0001 _
b0001 `
1b
1e
1g
1h
1i
b01 k
b00010000000000000000000000000000 l
1n
#7
0n
#8
b00000000000000000000000000001111 .
1/
b00000000000000000000000000000000 2
b00000000000000000000000000000000 3
b0000 4
06
07
18
b00000000000000000000000000000000 9
b0000 ;
0=
0>
b00000000000000000000000000000000 A
b0000 C
0F
b00000000000000000000000000000000 G
b0000 I
0L
b0100 N
b0101 O
b00000000000000000000000000001111 S
1V
b00000000000000000000000000000000 X
b00000000000000000000000000000000 Y
b00000000000000000000000000000000 Z
b0000 ^
b0000 _
b0000 `
0e
0g
0h
0i
b00010000000000000000000000000000 m
1n
b1111 p
b00000000000000000000000000001111 q
#9
0n
#10
0/
05
08
0<
b0101 N
b0000 O
0V
0b
1n
#11
0n
#12
b11011110101011011011111011101111 .
b00100000000000000000000000000000 3
15
16
1D
1E
b0000 N
b0001 O
1c
1f
b10 k
b00100000000000000000000000000000 l
1n
#13
0n
#14
1/
b00000000000000000000000000000000 3
06
1@
0E
b0001 N
b0010 O
1W
0f
b00100000000000000000000000000000 m
1n
#15
0n
#16
0/
05
0@
0D
b0010 N
b0011 O
0W
0c
1n
#17
0n
#18
b00000000000000000000000000001111 .
b11011110101011011011111011101111 2
b00010000000000000000000000000000 3
b0001 4
15
16
17
b11011110101011011011111011101111 9
b0001 ;
1<
1=
1>
b11011110101011011011111011101111 A
b0001 C
1F
b11011110101011011011111011101111 G
b0001 I
1L
b0011 N
b0100 O
b11011110101011011011111011101111 X
b11011110101011011011111011101111 Y
b11011110101011011011111011101111 Z
b0001 ^
b0001 _
b0001 `
1b
1e
1g
1h
1i
b01 k
b00010000000000000000000000000000 l
1n
#19
0n
#20
1/
b00000000000000000000000000000000 2
b00000000000000000000000000000000 3
b0000 4
06
07
18
b00000000000000000000000000000000 9
b0000 ;
0=
0>
b00000000000000000000000000000000 A
b0000 C
0F
b00000000000000000000000000000000 G
b0000 I
0L
b0100 N
b0101 O
1V
b00000000000000000000000000000000 X
b00000000000000000000000000000000 Y
b00000000000000000000000000000000 Z
b0000 ^
b0000 _
b0000 `
0e
0g
0h
0i
b00010000000000000000000000000000 m
1n
#21
0n
#22
0/
05
08
0<
b0101 N
b0000 O
0V
0b
1n
#23
0n
#24
b11011110101011011011111011101111 .
b00100000000000000000000000000000 3
15
16
1D
1E
b0000 N
b0001 O
1c
1f
b10 k
b00100000000000000000000000000000 l
1n
#25
0n
#26
1/
b00000000000000000000000000000000 3
06
1@
0E
b0001 N
b0010 O
1W
0f
b00100000000000000000000000000000 m
1n
#27
0n
#28
0/
05
0@
0D
b0010 N
b0011 O
0W
0c
1n
#29
0n
#30
b00000000000000000000000000001111 .
b11011110101011011011111011101111 2
b00010000000000000000000000000000 3
b0001 4
15
16
17
b11011110101011011011111011101111 9
b0001 ;
1<
1=
1>
b11011110101011011011111011101111 A
b0001 C
1F
b11011110101011011011111011101111 G
b0001 I
1L
b0011 N
b0100 O
b11011110101011011011111011101111 X
b11011110101011011011111011101111 Y
b11011110101011011011111011101111 Z
b0001 ^
b0001 _
b0001 `
1b
1e
1g
1h
1i
b01 k
b00010000000000000000000000000000 l
1n
#31
0n
#32
1/
b00000000000000000000000000000000 2
b00000000000000000000000000000000 3
b0000 4
06
07
18
b00000000000000000000000000000000 9
b0000 ;
0=
0>
b00000000000000000000000000000000 A
b0000 C
0F
b00000000000000000000000000000000 G
b0000 I
0L
b0100 N
b0101 O
1V
b00000000000000000000000000000000 X
b00000000000000000000000000000000 Y
b00000000000000000000000000000000 Z
b0000 ^
b0000 _
b0000 `
0e
0g
0h
0i
b00010000000000000000000000000000 m
1n
#33
0n
#34
0/
05
08
0<
b0101 N
b0000 O
0V
0b
1n
#35
0n
#36
b11011110101011011011111011101111 .
b00100000000000000000000000000000 3
15
16
1D
1E
b0000 N
b0001 O
1c
1f
b10 k
b00100000000000000000000000000000 l
1n
#37
0n
#38
1/
b00000000000000000000000000000000 3
06
1@
0E
b0001 N
b0010 O
1W
0f
b00100000000000000000000000000000 m
1n
#39
0n
#40
0/
05
0@
0D
b0010 N
b0011 O
0W
0c
1n
#41
0n
#42
b00000000000000000000000000001111 .
b11011110101011011011111011101111 2
b00010000000000000000000000000000 3
b0001 4
15
16
17
b11011110101011011011111011101111 9
b0001 ;
1<
1=
1>
b11011110101011011011111011101111 A
b0001 C
1F
b11011110101011011011111011101111 G
b0001 I
1L
b0011 N
b0100 O
b11011110101011011011111011101111 X
b11011110101011011011111011101111 Y
b11011110101011011011111011101111 Z
b0001 ^
b0001 _
b0001 `
1b
1e
1g
1h
1i
b01 k
b00010000000000000000000000000000 l
1n
#43
0n
#44
1/
b00000000000000000000000000000000 2
b00000000000000000000000000000000 3
b0000 4
06
07
18
b00000000000000000000000000000000 9
b0000 ;
0=
0>
b00000000000000000000000000000000 A
b0000 C
0F
b00000000000000000000000000000000 G
b0000 I
0L
b0100 N
b0101 O
1V
b00000000000000000000000000000000 X
b00000000000000000000000000000000 Y
b00000000000000000000000000000000 Z
b0000 ^
b0000 _
b0000 `
0e
0g
0h
0i
b00010000000000000000000000000000 m
1n
#45
0n
#46
0/
05
08
0<
b0101 N
b0000 O
0V
0b
1n
#47
0n
#48
b11011110101011011011111011101111 .
b00100000000000000000000000000000 3
15
16
1D
1E
b0000 N
b0001 O
1c
1f
b10 k
b00100000000000000000000000000000 l
1n
#49
0n
#50
1/
b00000000000000000000000000000000 3
06
1@
0E
b0001 N
b0010 O
1W
0f
b00100000000000000000000000000000 m
1n
#51
0n
#52
0/
05
0@
0D
b0010 N
b0011 O
0W
0c
1n
#53
0n
#54
b00000000000000000000000000001111 .
b11011110101011011011111011101111 2
b00010000000000000000000000000000 3
b0001 4
15
16
17
b11011110101011011011111011101111 9
b0001 ;
1<
1=
1>
b11011110101011011011111011101111 A
b0001 C
1F
b11011110101011011011111011101111 G
b0001 I
1L
b0011 N
b0100 O
b11011110101011011011111011101111 X
b11011110101011011011111011101111 Y
b11011110101011011011111011101111 Z
b0001 ^
b0001 _
b0001 `
1b
1e
1g
1h
1i
b01 k
b00010000000000000000000000000000 l
1n
#55
0n
#56
1/
b00000000000000000000000000000000 2
b00000000000000000000000000000000 3
b0000 4
06
07
18
b00000000000000000000000000000000 9
b0000 ;
0=
0>
b00000000000000000000000000000000 A
b0000 C
0F
b00000000000000000000000000000000 G
b0000 I
0L
b0100 N
b0101 O
1V
b00000000000000000000000000000000 X
b00000000000000000000000000000000 Y
b00000000000000000000000000000000 Z
b0000 ^
b0000 _
b0000 `
0e
0g
0h
0i
b00010000000000000000000000000000 m
1n
#57
0n
#58
0/
05
08
0<
b0101 N
b0000 O
0V
0b
1n
#59
0n
#60
b11011110101011011011111011101111 .
b00100000000000000000000000000000 3
15
16
1D
1E
b0000 N
b0001 O
1c
1f
b10 k
b00100000000000000000000000000000 l
1n
#61
0n
#62
1/
b00000000000000000000000000000000 3
06
1@
0E
b0001 N
b0010 O
1W
0f
b00100000000000000000000000000000 m
1n
#63
0n
#64
0/
05
0@
0D
b0010 N
b0011 O
0W
0c
1n
#65
0n
#66
b00000000000000000000000000001111 .
b11011110101011011011111011101111 2
b00010000000000000000000000000000 3
b0001 4
15
16
17
b11011110101011011011111011101111 9
b0001 ;
1<
1=
1>
b11011110101011011011111011101111 A
b0001 C
1F
b11011110101011011011111011101111 G
b0001 I
1L
b0011 N
b0100 O
b11011110101011011011111011101111 X
b11011110101011011011111011101111 Y
b11011110101011011011111011101111 Z
b0001 ^
b0001 _
b0001 `
1b
1e
1g
1h
1i
b01 k
b00010000000000000000000000000000 l
1n
#67
0n
#68
1/
b00000000000000000000000000000000 2
b00000000000000000000000000000000 3
b0000 4
06
07
18
b00000000000000000000000000000000 9
b0000 ;
0=
0>
b00000000000000000000000000000000 A
b0000 C
0F
b00000000000000000000000000000000 G
b0000 I
0L
b0100 N
b0101 O
1V
b00000000000000000000000000000000 X
b00000000000000000000000000000000 Y
b00000000000000000000000000000000 Z
b0000 ^
b0000 _
b0000 `
0e
0g
0h
0i
b00010000000000000000000000000000 m
1n
#69
0n
#70
0/
05
08
0<
b0101 N
b0000 O
0V
0b
1n
#71
0n
#72
b11011110101011011011111011101111 .
b00100000000000000000000000000000 3
15
16
1D
1E
b0000 N
b0001 O
1c
1f
b10 k
b00100000000000000000000000000000 l
1n
#73
0n
#74
1/
b00000000000000000000000000000000 3
06
1@
0E
b0001 N
b0010 O
1W
0f
b00100000000000000000000000000000 m
1n
#75
0n
#76
0/
05
0@
0D
b0010 N
b0011 O
0W
0c
1n
#77
0n
#78
b00000000000000000000000000001111 .
b11011110101011011011111011101111 2
b00010000000000000000000000000000 3
b0001 4
15
16
17
b11011110101011011011111011101111 9
b0001 ;
1<
1=
1>
b11011110101011011011111011101111 A
b0001 C
1F
b11011110101011011011111011101111 G
b0001 I
1L
b0011 N
b0100 O
b11011110101011011011111011101111 X
b11011110101011011011111011101111 Y
b11011110101011011011111011101111 Z
b0001 ^
b0001 _
b0001 `
1b
1e
1g
1h
1i
b01 k
b00010000000000000000000000000000 l
1n
#79
0n
#80
1/
b00000000000000000000000000000000 2
b00000000000000000000000000000000 3
b0000 4
06
07
18
b00000000000000000000000000000000 9
b0000 ;
0=
0>
b00000000000000000000000000000000 A
b0000 C
0F
b00000000000000000000000000000000 G
b0000 I
0L
b0100 N
b0101 O
1V
b00000000000000000000000000000000 X
b00000000000000000000000000000000 Y
b00000000000000000000000000000000 Z
b0000 ^
b0000 _
b0000 `
0e
0g
0h
0i
b00010000000000000000000000000000 m
1n
#81
0n
#82
0/
05
08
0<
b0101 N
b0000 O
0V
0b
1n
#83
0n
#84
b11011110101011011011111011101111 .
b00100000000000000000000000000000 3
15
16
1D
1E
b0000 N
b0001 O
1c
1f
b10 k
b00100000000000000000000000000000 l
1n
#85
0n
#86
1/
b00000000000000000000000000000000 3
06
1@
0E
b0001 N
b0010 O
1W
0f
b00100000000000000000000000000000 m
1n
#87
0n
#88
0/
05
0@
0D
b0010 N
b0011 O
0W
0c
1n
#89
0n
#90
b00000000000000000000000000001111 .
b11011110101011011011111011101111 2
b00010000000000000000000000000000 3
b0001 4
15
16
17
b11011110101011011011111011101111 9
b0001 ;
1<
1=
1>
b11011110101011011011111011101111 A
b0001 C
1F
b11011110101011011011111011101111 G
b0001 I
1L
b0011 N
b0100 O
b11011110101011011011111011101111 X
b11011110101011011011111011101111 Y
b11011110101011011011111011101111 Z
b0001 ^
b0001 _
b0001 `
1b
1e
1g
1h
1i
b01 k
b00010000000000000000000000000000 l
1n
#91
0n
